{"meta": {"date": "2022-07-01", "version": "5.2.0+20220701"}, "data": {"code": "EXO", "commander": [], "mainBoard": [{"artist": "Tom Wänerstrand", "availability": ["paper"], "boosterTypes": ["draft"], "borderColor": "white", "colorIdentity": [], "colors": [], "convertedManaCost": 0.0, "count": 1, "edhrecRank": 97, "finishes": ["nonfoil"], "foreignData": [{"language": "German", "name": "Messingstadt", "text": "Immer wenn die Messingstadt getappt wird, fügt sie Dir 1 Schadenspunkt zu.\n{T}: Erhöhe Deinen Manavorrat um ein Mana einer beliebigen Farbe.", "type": "Land"}, {"language": "Spanish", "name": "Ciudad de bronce"}, {"language": "French", "name": "Cité d'airain"}, {"language": "Italian", "name": "Città d'Ottone"}, {"language": "Japanese", "name": "真鍮の都"}, {"language": "Portuguese (Brazil)", "name": "Cidade de Bronze"}], "frameVersion": "1997", "hasFoil": false, "hasNonFoil": true, "identifiers": {"cardKingdomId": "11069", "cardsphereId": "1217", "mcmId": "9784", "mcmMetaId": "1009", "mtgjsonV4Id": "482664ed-6b36-55a1-8674-56e8f25e3dd2", "multiverseId": "4178", "scryfallId": "56816a2d-4faa-4fbd-bf1a-35fa3e90ccf6", "scryfallIllustrationId": "f10ccb2b-fd72-4725-a9eb-83ee83a36558", "scryfallOracleId": "f25351e3-539b-4bbc-b92d-6480acf4d722", "tcgplayerProductId": "2077"}, "isFoil": false, "isReprint": true, "language": "English", "layout": "normal", "legalities": {"commander": "Legal", "duel": "Legal", "legacy": "Legal", "modern": "Legal", "premodern": "Legal", "vintage": "Legal"}, "manaValue": 0.0, "name": "City of Brass", "number": "413", "printings": ["2X2", "5ED", "6ED", "7ED", "8ED", "ARN", "CHR", "MD1", "ME4", "MMA", "PRM", "PSUS", "PTC", "RIN", "WC00", "WC01", "WC02", "WC03", "WC97", "WC98"], "purchaseUrls": {"cardKingdom": "https://mtgjson.com/links/597a7ddb9357e913", "cardmarket": "https://mtgjson.com/links/a47ea0fafc51ef04", "tcgplayer": "https://mtgjson.com/links/d411fbdc848f3c90"}, "rarity": "rare", "rulings": [{"date": "2004-10-04", "text": "The first ability triggers no matter how the land becomes tapped."}, {"date": "2004-10-04", "text": "If you tap City of Brass while you are casting a spell or activating an ability, its ability will trigger and wait. When you finish casting that spell or activating that ability, City of Brass’s triggered ability is put on the stack on top of it. City of Brass’s ability will resolve first."}, {"date": "2004-10-04", "text": "On the other hand, you can tap City of Brass, put its triggered ability on the stack, and then respond to that ability by casting an instant or activating an ability using that mana. In that case, the instant spell or activated ability will resolve first."}], "setCode": "5ED", "subtypes": [], "supertypes": [], "text": "Whenever City of Brass becomes tapped, it deals 1 damage to you.\n{T}: Add one mana of any color.", "type": "Land", "types": ["Land"], "uuid": "565bf8b1-3d78-53dc-abac-a9d9ed2fdb0e"}, {"artist": "Douglas Shuler", "availability": ["mtgo", "paper"], "boosterTypes": ["draft"], "borderColor": "black", "colorIdentity": ["G"], "colors": [], "convertedManaCost": 0.0, "count": 1, "finishes": ["nonfoil"], "foreignData": [{"language": "German", "name": "Wald"}, {"language": "Spanish", "name": "Bosque"}, {"language": "French", "name": "Forêt"}, {"language": "Italian", "name": "Foresta"}, {"language": "Japanese", "name": "森"}, {"language": "Portuguese (Brazil)", "name": "Floresta"}], "frameVersion": "1997", "hasFoil": false, "hasNonFoil": true, "identifiers": {"cardKingdomId": "192753", "cardsphereId": "43178", "mcmId": "9043", "mcmMetaId": "2177", "mtgjsonV4Id": "32c0ad5f-e9a4-5393-9574-312651d64069", "mtgoFoilId": "9696", "mtgoId": "9695", "multiverseId": "4926", "scryfallId": "36b3ffbd-3f3e-4fca-80c2-94f9fdc198a5", "scryfallIllustrationId": "0c152dd9-b6ff-4646-8df2-7bd806c3471a", "scryfallOracleId": "b34bb2dc-c1af-4d77-b0b3-a0fb342a5fc6", "tcgplayerProductId": "18487"}, "isFoil": false, "isReprint": true, "language": "English", "layout": "normal", "legalities": {"alchemy": "Legal", "brawl": "Legal", "commander": "Legal", "duel": "Legal", "explorer": "Legal", "future": "Legal", "gladiator": "Legal", "historic": "Legal", "historicbrawl": "Legal", "legacy": "Legal", "modern": "Legal", "pauper": "Legal", "paupercommander": "Legal", "penny": "Legal", "pioneer": "Legal", "premodern": "Legal", "standard": "Legal", "vintage": "Legal"}, "manaValue": 0.0, "name": "Forest", "number": "347", "printings": ["10E", "2ED", "2XM", "3ED", "4BB", "4ED", "5ED", "6ED", "7ED", "8ED", "9ED", "AFR", "AKH", "AKR", "ALA", "ANA", "ANB", "ARC", "ATH", "AVR", "BBD", "BFZ", "BRB", "BTD", "C13", "C14", "C15", "C16", "C17", "C18", "C19", "CED", "CEI", "CHK", "CLB", "CM2", "CMA", "CMD", "CMR", "CST", "DD1", "DDD", "DDE", "DDG", "DDH", "DDJ", "DDL", "DDM", "DDO", "DDP", "DDR", "DDS", "DDU", "DKM", "DOM", "DPA", "DTK", "E01", "ELD", "EVG", "FBB", "FRF", "G17", "GK1", "GK2", "GN2", "GNT", "GRN", "GS1", "GVL", "H09", "HOP", "HOU", "ICE", "IKO", "INV", "ISD", "ITP", "J14", "JMP", "KHM", "KLD", "KLR", "KTK", "LEA", "LEB", "LRW", "M10", "M11", "M12", "M13", "M14", "M15", "M19", "M20", "M21", "MBS", "ME1", "ME3", "MH2", "MID", "MIR", "MMQ", "MRD", "NEO", "NPH", "ODY", "ONS", "ORI", "P02", "PAL00", "PAL01", "PAL03", "PAL04", "PAL05", "PAL06", "PAL99", "PALP", "PANA", "PARL", "PC2", "PCA", "PELP", "PF19", "PF20", "PGPX", "PGRU", "PMPS", "PMPS06", "PMPS07", "PMPS08", "PMPS09", "PMPS10", "PMPS11", "POR", "PPP1", "PRM", "PRW2", "PRWK", "PS11", "PSAL", "PSS2", "PSS3", "PTC", "PTK", "PZ2", "RAV", "RIX", "RNA", "ROE", "RQS", "RTR", "S99", "SHM", "SLD", "SNC", "SOI", "SOM", "STX", "SUM", "TD0", "TD2", "THB", "THS", "TMP", "TPR", "TSP", "UGL", "UND", "UNF", "UNH", "USG", "UST", "VOW", "WAR", "WC00", "WC01", "WC02", "WC03", "WC04", "WC97", "WC98", "WC99", "XANA", "XLN", "ZEN", "ZNR"], "purchaseUrls": {"cardKingdom": "https://mtgjson.com/links/b46c93d0f73e133b", "cardmarket": "https://mtgjson.com/links/29cf07a0ea7adb20", "tcgplayer": "https://mtgjson.com/links/79f5a43ffbf6256d"}, "rarity": "common", "rulings": [], "setCode": "TMP", "subtypes": ["Forest"], "supertypes": ["Basic"], "text": "({T}: Add {G}.)", "type": "Basic Land — Forest", "types": ["Land"], "uuid": "bba765cb-187a-58eb-b976-fb7b7942142c", "variations": ["c5b0850e-b467-5a6a-a3db-0af6027e7e9e", "5ff15278-d1d0-5487-9122-a26d6f088b97", "26981e7a-8dff-55f6-bc90-bcdbdd93c7d3"]}, {"artist": "Randy Gallegos", "availability": ["paper"], "boosterTypes": ["draft"], "borderColor": "white", "colorIdentity": ["G", "R"], "colors": [], "convertedManaCost": 0.0, "count": 2, "edhrecRank": 861, "finishes": ["nonfoil"], "foreignData": [{"language": "German", "name": "Karplusanischer Wald", "text": "{T}: Erhöhe Deinen Manavorrat um ein farbloses Mana.\n{T}: Erhöhe Deinen Manavorrat um {R} oder G. Der Karplusanische Wald fügt Dir 1 Schadenspunkt zu.", "type": "Land"}, {"language": "Spanish", "name": "Foresta karplusana"}, {"language": "French", "name": "Forêt de Karpluse"}, {"language": "Italian", "name": "Foresta di Karplus"}, {"language": "Japanese", "name": "カープルーザンの森"}, {"language": "Portuguese (Brazil)", "name": "Floresta Karplusana"}], "frameVersion": "1997", "hasFoil": false, "hasNonFoil": true, "identifiers": {"cardKingdomId": "11225", "cardsphereId": "1378", "mcmId": "9800", "mcmMetaId": "3030", "mtgjsonV4Id": "bc09d43d-337b-5c8e-8f01-c6c5c117e3ae", "multiverseId": "4186", "scryfallId": "38d59e6e-0154-4c89-a58f-521e3424581b", "scryfallIllustrationId": "23feb2fa-5905-4517-9a4d-e00587ac02d1", "scryfallOracleId": "bd912666-f37f-4767-af6f-9e6d0fcccacf", "tcgplayerProductId": "2238"}, "isFoil": false, "isReprint": true, "language": "English", "layout": "normal", "legalities": {"commander": "Legal", "duel": "Legal", "legacy": "Legal", "modern": "Legal", "premodern": "Legal", "vintage": "Legal"}, "manaValue": 0.0, "name": "Karplusan Forest", "number": "421", "printings": ["10E", "5ED", "6ED", "7ED", "9ED", "C16", "DKM", "ICE", "PTC", "WC00", "WC01", "WC02", "WC98"], "purchaseUrls": {"cardKingdom": "https://mtgjson.com/links/3baefbf0451e00f8", "cardmarket": "https://mtgjson.com/links/f5671886f9682fb7", "tcgplayer": "https://mtgjson.com/links/35aebdd2e999a174"}, "rarity": "rare", "rulings": [], "setCode": "5ED", "subtypes": [], "supertypes": [], "text": "{T}: Add {C}.\n{T}: Add {R} or {G}. Karplusan Forest deals 1 damage to you.", "type": "Land", "types": ["Land"], "uuid": "2569780a-88ef-5db2-a9bf-a19e959d9793"}, {"artist": "Mark Poole", "availability": ["mtgo", "paper"], "boosterTypes": ["draft"], "borderColor": "black", "colorIdentity": ["R"], "colors": [], "convertedManaCost": 0.0, "count": 3, "finishes": ["nonfoil"], "foreignData": [{"language": "German", "name": "Gebirge"}, {"language": "Spanish", "name": "Montaña"}, {"language": "French", "name": "Montagne"}, {"language": "Italian", "name": "Montagna"}, {"language": "Japanese", "name": "山"}, {"language": "Portuguese (Brazil)", "name": "Montanha"}], "frameVersion": "1997", "hasFoil": false, "hasNonFoil": true, "identifiers": {"cardKingdomId": "192759", "cardsphereId": "43262", "mcmId": "9054", "mcmMetaId": "3743", "mtgjsonV4Id": "e45f79f8-26a4-5cbb-af94-a78e712d449e", "mtgoFoilId": "9694", "mtgoId": "9693", "multiverseId": "4948", "scryfallId": "9d6dc341-89dc-4e99-baa2-ad0ae59f0e94", "scryfallIllustrationId": "1f96347b-4854-404c-939c-1c2b7758073d", "scryfallOracleId": "a3fb7228-e76b-4e96-a40e-20b5fed75685", "tcgplayerProductId": "18493"}, "isFoil": false, "isReprint": true, "language": "English", "layout": "normal", "legalities": {"alchemy": "Legal", "brawl": "Legal", "commander": "Legal", "duel": "Legal", "explorer": "Legal", "future": "Legal", "gladiator": "Legal", "historic": "Legal", "historicbrawl": "Legal", "legacy": "Legal", "modern": "Legal", "pauper": "Legal", "paupercommander": "Legal", "penny": "Legal", "pioneer": "Legal", "premodern": "Legal", "standard": "Legal", "vintage": "Legal"}, "manaValue": 0.0, "name": "Mountain", "number": "343", "printings": ["10E", "2ED", "2XM", "3ED", "4BB", "4ED", "5ED", "6ED", "7ED", "8ED", "9ED", "AFR", "AKH", "AKR", "ALA", "ANA", "ANB", "ARC", "ARN", "ATH", "AVR", "BBD", "BFZ", "BRB", "BTD", "C13", "C14", "C15", "C16", "C17", "C18", "C19", "CED", "CEI", "CHK", "CLB", "CM2", "CMA", "CMD", "CMR", "CST", "DD1", "DD2", "DDE", "DDG", "DDH", "DDI", "DDJ", "DDK", "DDL", "DDN", "DDP", "DDS", "DDT", "DDU", "DKM", "DOM", "DPA", "DTK", "E01", "ELD", "EVG", "FBB", "FRF", "G17", "GK1", "GK2", "GN2", "GNT", "GRN", "GS1", "H09", "HOP", "HOU", "ICE", "IKO", "INV", "ISD", "ITP", "J14", "JMP", "JVC", "KHM", "KLD", "KLR", "KTK", "LEA", "LEB", "LRW", "M10", "M11", "M12", "M13", "M14", "M15", "M19", "M20", "M21", "MBS", "ME1", "ME3", "MH2", "MID", "MIR", "MMQ", "MRD", "NEO", "NPH", "ODY", "ONS", "ORI", "P02", "PAL00", "PAL01", "PAL03", "PAL04", "PAL05", "PAL06", "PAL99", "PALP", "PANA", "PARL", "PC2", "PCA", "PD2", "PELP", "PF19", "PF20", "PGPX", "PGRU", "PHED", "PLIST", "PMPS", "PMPS06", "PMPS07", "PMPS08", "PMPS09", "PMPS10", "PMPS11", "POR", "PPP1", "PRM", "PRW2", "PRWK", "PS11", "PSAL", "PSS2", "PSS3", "PTC", "PTK", "PZ2", "RAV", "RIX", "RNA", "ROE", "RQS", "RTR", "S99", "SHM", "SLD", "SNC", "SOI", "SOM", "STX", "SUM", "TD0", "THB", "THS", "TMP", "TPR", "TSP", "UGL", "UND", "UNF", "UNH", "USG", "UST", "VOW", "WAR", "WC00", "WC01", "WC02", "WC03", "WC97", "WC98", "WC99", "XANA", "XLN", "ZEN", "ZNR"], "purchaseUrls": {"cardKingdom": "https://mtgjson.com/links/adabcb0af77f649a", "cardmarket": "https://mtgjson.com/links/3c8cf4299850b4bc", "tcgplayer": "https://mtgjson.com/links/18b5e708dafaef98"}, "rarity": "common", "rulings": [], "setCode": "TMP", "subtypes": ["Mountain"], "supertypes": ["Basic"], "text": "({T}: Add {R}.)", "type": "Basic Land — Mountain", "types": ["Land"], "uuid": "b491f8f6-1349-5a15-8814-f7642bc35d17", "variations": ["09ff5e23-3a99-546d-8eaf-e72de329f23e", "a87d8455-9b61-5e88-aea2-63d60da77407", "40273ea8-5c14-5791-9ac1-69e05efa4773"]}, {"artist": "Roger Raupp", "availability": ["mtgo", "paper"], "boosterTypes": ["draft"], "borderColor": "black", "colorIdentity": [], "colors": [], "convertedManaCost": 0.0, "count": 3, "edhrecRank": 9680, "finishes": ["nonfoil"], "foreignData": [{"language": "German", "name": "Treibsand", "text": "{T}: Erhöhe Deinen Manavorrat um ein farbloses Mana.\n{T}, opfere den Treibsand: Eine angreifende nichtfliegende Kreatur Deiner Wahl erhält -1/-2 bis zum Ende des Zuges.", "type": "Land"}, {"language": "Spanish", "name": "Arenas movedizas"}, {"language": "French", "name": "Sables mouvants"}, {"language": "Italian", "name": "Sabbie Mobili"}, {"language": "Japanese", "name": "流砂"}, {"language": "Portuguese (Brazil)", "name": "Areia Movediça"}], "frameVersion": "1997", "hasFoil": false, "hasNonFoil": true, "identifiers": {"cardKingdomId": "32103", "cardsphereId": "46930", "mcmId": "8567", "mcmMetaId": "4432", "mtgjsonV4Id": "a590c4ca-d3c2-5c42-a32c-ea7d5560ce27", "mtgoFoilId": "7678", "mtgoId": "7677", "multiverseId": "3754", "scryfallId": "11370658-8d80-4d2f-afa5-ec6df6dee369", "scryfallIllustrationId": "0622efea-1e51-4449-8a28-9b28b996889c", "scryfallOracleId": "ef2bb4fa-f292-4d19-aaa4-cfbe445caf45", "tcgplayerProductId": "5904"}, "isFoil": false, "language": "English", "layout": "normal", "legalities": {"commander": "Legal", "duel": "Legal", "legacy": "Legal", "modern": "Legal", "pauper": "Legal", "paupercommander": "Legal", "penny": "Legal", "premodern": "Legal", "vintage": "Legal"}, "manaValue": 0.0, "name": "Quicksand", "number": "166", "printings": ["10E", "9ED", "A25", "CNS", "VIS", "WC98", "WWK"], "purchaseUrls": {"cardKingdom": "https://mtgjson.com/links/7ae9291947eae9d4", "cardmarket": "https://mtgjson.com/links/8e24f1cf983b9006", "tcgplayer": "https://mtgjson.com/links/07df8f224993df24"}, "rarity": "uncommon", "rulings": [], "setCode": "VIS", "subtypes": [], "supertypes": [], "text": "{T}: Add {C}.\n{T}, Sacrifice Quicksand: Target attacking creature without flying gets -1/-2 until end of turn.", "type": "Land", "types": ["Land"], "uuid": "9ea5b7eb-b25d-59b2-93ed-0ecfb78f8ac4"}, {"artist": "Adam Rex", "availability": ["mtgo", "paper"], "boosterTypes": ["draft"], "borderColor": "black", "colorIdentity": [], "colors": [], "convertedManaCost": 0.0, "count": 3, "edhrecRank": 260, "finishes": ["nonfoil"], "flavorText": "\"The reflection of land interests me far more than its reality.\"\n—Volrath", "foreignData": [{"language": "German", "name": "Widerspiegelnder Teich", "text": "{T}: Erhöhe Deinen Manavorrat um ein Mana eines Typs, welches ein Land, das Du kontrollierst, produzieren kann.", "type": "Land"}, {"language": "Spanish", "name": "Estanque reflectante"}, {"language": "French", "name": "Bassin réfléchissant"}, {"language": "Italian", "name": "Pozza Riflettente"}, {"language": "Japanese", "name": "反射池"}, {"language": "Portuguese (Brazil)", "name": "Lagoa Espelhada"}], "frameVersion": "1997", "hasFoil": false, "hasNonFoil": true, "identifiers": {"cardKingdomId": "28229", "cardsphereId": "43306", "mcmId": "9063", "mcmMetaId": "4595", "mtgjsonV4Id": "c6ac4d4a-d49e-5891-a351-ffb090b482d7", "mtgoFoilId": "9846", "mtgoId": "9845", "multiverseId": "4936", "scryfallId": "7b633ac2-bf98-42bd-8c26-8737a7d8edc7", "scryfallIllustrationId": "4fc67298-6610-47d7-971b-baf5728d5349", "scryfallOracleId": "67f43ac6-2a58-4b53-b5d7-0330e2a252e2", "tcgplayerProductId": "5688"}, "isFoil": false, "language": "English", "layout": "normal", "legalities": {"commander": "Legal", "duel": "Legal", "legacy": "Legal", "modern": "Legal", "premodern": "Legal", "vintage": "Legal"}, "manaValue": 0.0, "name": "Reflecting Pool", "number": "322", "printings": ["CLB", "CNS", "J19", "PCLB", "PRM", "SHM", "TMP", "WC98"], "purchaseUrls": {"cardKingdom": "https://mtgjson.com/links/97bce463ed83151d", "cardmarket": "https://mtgjson.com/links/d6fa7becc4638937", "tcgplayer": "https://mtgjson.com/links/19adb0c1b286ddd0"}, "rarity": "rare", "rulings": [{"date": "2004-10-04", "text": "Any replacement effects are considered by Reflecting Pool when determining the types of mana a land can produce."}, {"date": "2004-10-04", "text": "Any change to a land’s type or splicing of text into a land can affect the types of mana a land can produce."}, {"date": "2008-05-01", "text": "The types of mana are white, blue, black, red, green, and colorless."}, {"date": "2008-05-01", "text": "Reflecting Pool checks the effects of all mana-producing abilities of lands you control, but it doesn’t check their costs. For example, Vivid Crag says “{T}, Remove a charge counter from Vivid Crag: Add one mana of any color.” If you control Vivid Crag and Reflecting Pool, you can tap Reflecting Pool for any color of mana. It doesn’t matter whether Vivid Crag has a charge counter on it, and it doesn’t matter whether it’s untapped."}, {"date": "2008-05-01", "text": "Reflecting Pool doesn’t care about any restrictions or riders your lands put on the mana they produce, such as Pillar of the Paruns and Hall of the Bandit Lord do. It just cares about types of mana."}, {"date": "2008-05-01", "text": "Multiple Reflecting Pools won’t help each other produce mana. If you control a Reflecting Pool, and all other lands you control either lack mana abilities or are other Reflecting Pools, you may still activate Reflecting Pool’s ability — it just won’t produce any mana."}], "setCode": "TMP", "subtypes": [], "supertypes": [], "text": "{T}: Add one mana of any type that a land you control could produce.", "type": "Land", "types": ["Land"], "uuid": "76a83d04-c864-5274-8cf3-54e48a653ae4"}, {"artist": "Jeff Miracola", "availability": ["paper"], "boosterTypes": ["draft"], "borderColor": "white", "colorIdentity": ["B", "R"], "colors": [], "convertedManaCost": 0.0, "count": 2, "edhrecRank": 814, "finishes": ["nonfoil"], "foreignData": [{"language": "German", "name": "Schwefelquellen", "text": "{T}: Erhöhe Deinen Manavorrat um ein farbloses Mana.\n{T}: Erhöhe Deinen Manavorrat um {B} oder R. Die Schwefelquellen fügen Dir 1 Schadenspunkt zu.", "type": "Land"}, {"language": "Spanish", "name": "Manantiales sulfurosos"}, {"language": "French", "name": "Sources sulfureuses"}, {"language": "Italian", "name": "Sorgenti Sulfuree"}, {"language": "Japanese", "name": "硫黄泉"}, {"language": "Portuguese (Brazil)", "name": "Fontes Sulfurosas"}], "frameVersion": "1997", "hasFoil": false, "hasNonFoil": true, "identifiers": {"cardKingdomId": "11372", "cardsphereId": "1531", "mcmId": "9811", "mcmMetaId": "5694", "mtgjsonV4Id": "3db55201-0c8c-52d9-a350-37ee28fb750c", "multiverseId": "4189", "scryfallId": "85a2097d-5acb-46d5-ac07-021fa9da4026", "scryfallIllustrationId": "892943cd-3da6-4305-b6fb-3f4b25425390", "scryfallOracleId": "f5c38c01-4a40-469f-91a0-7479daf4e8e7", "tcgplayerProductId": "2391"}, "isFoil": false, "isReprint": true, "language": "English", "layout": "normal", "legalities": {"commander": "Legal", "duel": "Legal", "legacy": "Legal", "modern": "Legal", "premodern": "Legal", "vintage": "Legal"}, "manaValue": 0.0, "name": "Sulfurous Springs", "number": "424", "printings": ["10E", "5ED", "6ED", "7ED", "9ED", "DKM", "ICE", "PTC", "WC01", "WC97"], "purchaseUrls": {"cardKingdom": "https://mtgjson.com/links/86295d554022415d", "cardmarket": "https://mtgjson.com/links/e6308d17ee1c924c", "tcgplayer": "https://mtgjson.com/links/1c1dfc4327ff91ae"}, "rarity": "rare", "rulings": [], "setCode": "5ED", "subtypes": [], "supertypes": [], "text": "{T}: Add {C}.\n{T}: Add {B} or {R}. Sulfurous Springs deals 1 damage to you.", "type": "Land", "types": ["Land"], "uuid": "63221e47-a497-52bc-8a42-313b8c01a4a9"}, {"artist": "Brom", "availability": ["mtgo", "paper"], "boosterTypes": ["draft"], "borderColor": "black", "colorIdentity": ["B"], "colors": [], "convertedManaCost": 0.0, "count": 3, "finishes": ["nonfoil"], "foreignData": [{"language": "German", "name": "Sumpf"}, {"language": "Spanish", "name": "Pantano"}, {"language": "French", "name": "Marais"}, {"language": "Italian", "name": "Palude"}, {"language": "Japanese", "name": "沼"}, {"language": "Portuguese (Brazil)", "name": "Pântano"}], "frameVersion": "1997", "hasFoil": false, "hasNonFoil": true, "identifiers": {"cardKingdomId": "192763", "cardsphereId": "43378", "mcmId": "9069", "mcmMetaId": "5739", "mtgjsonV4Id": "17184710-0823-5a61-9562-01ea7e0479ca", "mtgoFoilId": "9692", "mtgoId": "9691", "multiverseId": "4923", "scryfallId": "5912d2aa-fe91-4cea-9c7a-6dca745f8560", "scryfallIllustrationId": "3c673130-6c43-41d6-9690-5c731fcec928", "scryfallOracleId": "56719f6a-1a6c-4c0a-8d21-18f7d7350b68", "tcgplayerProductId": "18499"}, "isFoil": false, "isReprint": true, "language": "English", "layout": "normal", "legalities": {"alchemy": "Legal", "brawl": "Legal", "commander": "Legal", "duel": "Legal", "explorer": "Legal", "future": "Legal", "gladiator": "Legal", "historic": "Legal", "historicbrawl": "Legal", "legacy": "Legal", "modern": "Legal", "pauper": "Legal", "paupercommander": "Legal", "penny": "Legal", "pioneer": "Legal", "premodern": "Legal", "standard": "Legal", "vintage": "Legal"}, "manaValue": 0.0, "name": "Swamp", "number": "339", "printings": ["10E", "2ED", "2XM", "3ED", "4BB", "4ED", "5ED", "6ED", "7ED", "8ED", "9ED", "AFR", "AKH", "AKR", "ALA", "ANA", "ANB", "ARC", "ATH", "AVR", "BBD", "BFZ", "BRB", "BTD", "C13", "C14", "C15", "C16", "C17", "C18", "C19", "CED", "CEI", "CHK", "CLB", "CM2", "CMA", "CMD", "CST", "DDC", "DDD", "DDE", "DDH", "DDJ", "DDK", "DDM", "DDN", "DDP", "DDQ", "DDR", "DKM", "DOM", "DPA", "DTK", "DVD", "E01", "ELD", "FBB", "FRF", "G17", "GK1", "GK2", "GN2", "GNT", "GRN", "GVL", "H09", "HOP", "HOU", "ICE", "IKO", "INV", "ISD", "ITP", "J14", "JMP", "KHM", "KLD", "KLR", "KTK", "LEA", "LEB", "LRW", "M10", "M11", "M12", "M13", "M14", "M15", "M19", "M20", "M21", "MBS", "MD1", "ME1", "ME3", "MH2", "MID", "MIR", "MMQ", "MRD", "NEO", "NPH", "ODY", "ONS", "ORI", "P02", "PAL00", "PAL01", "PAL03", "PAL04", "PAL05", "PAL06", "PAL99", "PALP", "PANA", "PARL", "PC2", "PCA", "PD3", "PELP", "PF19", "PF20", "PGPX", "PGRU", "PHUK", "PMPS", "PMPS06", "PMPS07", "PMPS08", "PMPS09", "PMPS10", "PMPS11", "POR", "PPP1", "PRM", "PRW2", "PRWK", "PS11", "PSAL", "PSS2", "PSS3", "PTC", "PTK", "RAV", "RIX", "RNA", "ROE", "RQS", "RTR", "S99", "SHM", "SLD", "SNC", "SOI", "SOM", "STX", "SUM", "TD0", "TD2", "THB", "THS", "TMP", "TPR", "TSP", "UGL", "UND", "UNF", "UNH", "USG", "UST", "VOW", "WAR", "WC01", "WC02", "WC03", "WC97", "WC98", "WC99", "XANA", "XLN", "ZEN", "ZNR"], "purchaseUrls": {"cardKingdom": "https://mtgjson.com/links/15665926d176e2b8", "cardmarket": "https://mtgjson.com/links/18060bd992cd92db", "tcgplayer": "https://mtgjson.com/links/6d7dd722c6c9b4e7"}, "rarity": "common", "rulings": [], "setCode": "TMP", "subtypes": ["Swamp"], "supertypes": ["Basic"], "text": "({T}: Add {B}.)", "type": "Basic Land — Swamp", "types": ["Land"], "uuid": "b3f49a68-1590-5e6b-95ef-15e3c9b340e9", "variations": ["e7f4cbbc-3c8f-5e82-a9a6-533b9b0debf7", "854e9559-122c-52d5-a5d6-186167ff9418", "b77d2bea-6adc-5f7a-9bc7-b37e988b6e82"]}, {"artist": "David O'Connor", "availability": ["mtgo", "paper"], "boosterTypes": ["draft"], "borderColor": "black", "colorIdentity": [], "colors": [], "convertedManaCost": 0.0, "count": 2, "edhrecRank": 10180, "finishes": ["nonfoil"], "flavorText": "Jolrael's choice of homes was far better than her choice of allies.", "foreignData": [{"language": "German", "name": "Unentdecktes Paradies", "text": "{T}: Erhöhe Deinen Manavorrat um ein Mana einer beliebigen Farbe. Bringe das Unentdeckte Paradies zu Beginn Deiner nächsten Enttap-Phase auf die Hand seines Besitzers zurück.", "type": "Land"}, {"language": "Spanish", "name": "Paraíso virgen"}, {"language": "French", "name": "Paradis inconnu"}, {"language": "Italian", "name": "Paradiso Nascosto"}, {"language": "Japanese", "name": "知られざる楽園"}, {"language": "Portuguese (Brazil)", "name": "Paraíso Inexplorado"}], "frameVersion": "1997", "hasFoil": false, "hasNonFoil": true, "identifiers": {"cardKingdomId": "32150", "cardsphereId": "46977", "mcmId": "8568", "mcmMetaId": "6217", "mtgjsonV4Id": "bf85e4b6-8b45-5bae-97f2-efa77885336b", "mtgoFoilId": "7772", "mtgoId": "7771", "multiverseId": "3755", "scryfallId": "5f6e8830-5e62-4945-8b73-60f0628d38e7", "scryfallIllustrationId": "d5b04f5c-f8d4-4133-ae49-51c682a45658", "scryfallOracleId": "76c33d54-ce55-400e-bec5-79d33a5a20fb", "tcgplayerProductId": "5951"}, "isFoil": false, "isReserved": true, "language": "English", "layout": "normal", "legalities": {"commander": "Legal", "duel": "Legal", "legacy": "Legal", "premodern": "Legal", "vintage": "Legal"}, "manaValue": 0.0, "name": "Undiscovered Paradise", "number": "167", "printings": ["PRM", "VIS", "WC97", "WC98"], "purchaseUrls": {"cardKingdom": "https://mtgjson.com/links/4194533ffdb1d87e", "cardmarket": "https://mtgjson.com/links/1fc46d1f68f80722", "tcgplayer": "https://mtgjson.com/links/871fff6dbd1cc57c"}, "rarity": "rare", "rulings": [{"date": "2004-10-04", "text": "It will return even if some effect prevents you from untapping it. The ability is not replacing the untapping of the land in any way."}, {"date": "2004-10-04", "text": "Only returns to owner’s hand if it is still on the battlefield at the beginning of its controller’s next untap."}], "setCode": "VIS", "subtypes": [], "supertypes": [], "text": "{T}: Add one mana of any color. During your next untap step, as you untap your permanents, return Undiscovered Paradise to its owner's hand.", "type": "Land", "types": ["Land"], "uuid": "9460969e-62f1-528e-b9ef-2d9aa7b2cc06"}, {"artist": "Una Fricker", "availability": ["mtgo", "paper"], "boosterTypes": ["draft"], "borderColor": "black", "colorIdentity": [], "colors": [], "convertedManaCost": 0.0, "count": 4, "edhrecRank": 752, "finishes": ["nonfoil"], "flavorText": "\"The land promises nothing and keeps its promise.\"\n—Oracle *en*-Vec", "foreignData": [{"language": "German", "name": "Einöde", "text": "{T}: Erhöhe Deinen Manavorrat um ein farbloses Mana.\n{T}, opfere die Einöde: Zerstöre ein Nicht-Standardland Deiner Wahl.", "type": "Land"}, {"language": "Spanish", "name": "Erial"}, {"language": "French", "name": "Terres dévastées"}, {"language": "Italian", "name": "Lande Desolate"}, {"language": "Japanese", "name": "不毛の大地"}, {"language": "Portuguese (Brazil)", "name": "Terras Ermas"}], "frameVersion": "1997", "hasFoil": false, "hasNonFoil": true, "identifiers": {"cardKingdomId": "28328", "cardsphereId": "43407", "mcmId": "9075", "mcmMetaId": "6538", "mtgjsonV4Id": "7a4ab440-0688-5022-8a0b-c1ca0afc0312", "mtgoFoilId": "10036", "mtgoId": "10035", "multiverseId": "4944", "scryfallId": "99ff731b-8399-40c8-b539-ba6ba5783771", "scryfallIllustrationId": "38cf1045-0520-4a67-a25e-dc7bb3acead6", "scryfallOracleId": "09a70ae8-3859-4a09-901d-dce063fa3b5f", "tcgplayerProductId": "5789"}, "isFoil": false, "language": "English", "layout": "normal", "legalities": {"commander": "Legal", "duel": "Banned", "legacy": "Legal", "premodern": "Legal", "vintage": "Legal"}, "manaValue": 0.0, "name": "Wasteland", "number": "330", "printings": ["EMA", "EXP", "G10", "J15", "MPR", "OLGC", "PRM", "SLD", "TMP", "TPR", "WC98", "WC99", "ZNE"], "purchaseUrls": {"cardKingdom": "https://mtgjson.com/links/bce815c754eb8cd1", "cardmarket": "https://mtgjson.com/links/c78db00e3949d847", "tcgplayer": "https://mtgjson.com/links/66e1eeb528cd8ab8"}, "rarity": "uncommon", "rulings": [], "setCode": "TMP", "subtypes": [], "supertypes": [], "text": "{T}: Add {C}.\n{T}, Sacrifice Wasteland: Destroy target nonbasic land.", "type": "Land", "types": ["Land"], "uuid": "2392456a-7a4a-5554-884f-b7ccaef08651"}, {"artist": "Brom", "availability": ["mtgo", "paper"], "boosterTypes": ["draft"], "borderColor": "black", "colorIdentity": ["R"], "colors": ["R"], "convertedManaCost": 5.0, "count": 2, "edhrecRank": 10881, "finishes": ["nonfoil"], "flavorText": "\"I'll take that. You won't need it when the revolution comes.\"", "foreignData": [{"language": "German", "name": "Anarchist", "text": "Wenn der Anarchist ins Spiel kommt, kannst Du eine Hexereikarte Deiner Wahl aus Deinem Friedhof zurück auf Deine Hand bringen.", "type": "Beschwörung von Stadtbewohnern"}, {"language": "Spanish", "name": "Anarquista"}, {"language": "French", "name": "Anarchiste"}, {"language": "Italian", "name": "Anarchico"}, {"language": "Japanese", "name": "無政府主義者"}, {"language": "Portuguese (Brazil)", "name": "Anarquista"}], "frameVersion": "1997", "hasFoil": false, "hasNonFoil": true, "identifiers": {"cardKingdomId": "17002", "cardsphereId": "17171", "mcmId": "9307", "mcmMetaId": "153", "mtgjsonV4Id": "1cbc62a3-3f88-5031-9396-5cb93ff4876a", "mtgoFoilId": "10702", "mtgoId": "10701", "multiverseId": "6110", "scryfallId": "a298df66-2075-40a7-bced-457656b6b788", "scryfallIllustrationId": "bacc96fb-730f-427c-874d-68fb8876d79c", "scryfallOracleId": "82b9ad93-df75-4417-9746-798db8fe6ba0", "tcgplayerProductId": "4293"}, "isFoil": false, "language": "English", "layout": "normal", "legalities": {"commander": "Legal", "duel": "Legal", "legacy": "Legal", "modern": "Legal", "pauper": "Legal", "paupercommander": "Legal", "penny": "Legal", "premodern": "Legal", "vintage": "Legal"}, "manaCost": "{4}{R}", "manaValue": 5.0, "name": "Anarchist", "number": "79", "power": "2", "printings": ["9ED", "EXO", "ODY", "TD0", "TPR"], "purchaseUrls": {"cardKingdom": "https://mtgjson.com/links/ad8a843a20c5db34", "cardmarket": "https://mtgjson.com/links/1e8d1f3a2e567836", "tcgplayer": "https://mtgjson.com/links/ed5f4ac672a98f7b"}, "rarity": "common", "rulings": [], "setCode": "EXO", "subtypes": ["Human", "Wizard"], "supertypes": [], "text": "When Anarchist enters the battlefield, you may return target sorcery card from your graveyard to your hand.", "toughness": "2", "type": "Creature — Human Wizard", "types": ["Creature"], "uuid": "2efaaaf9-beed-5d3f-95c0-bd48fb172d38"}, {"artist": "Geofrey Darrow & I. Rabarot", "availability": ["mtgo", "paper"], "boosterTypes": ["draft"], "borderColor": "black", "colorIdentity": ["B", "R"], "colors": ["B", "R"], "convertedManaCost": 3.0, "count": 1, "edhrecRank": 14793, "finishes": ["nonfoil"], "flavorText": "\"Do not underestimate the power of many against one.\"\n—Sidar Jabari", "foreignData": [{"language": "German", "name": "Kriegerameisen", "text": "{T}, opfere ein Land: Zerstöre ein Land Deiner Wahl.", "type": "Beschwörung von Insekten"}, {"language": "Spanish", "name": "Hormigas legionarias"}, {"language": "French", "name": "Fourmis guerrières"}, {"language": "Italian", "name": "Armata di Formiche"}, {"language": "Japanese", "name": "軍隊蟻"}, {"language": "Portuguese (Brazil)", "name": "Formigas de Correição"}], "frameVersion": "1997", "hasFoil": false, "hasNonFoil": true, "identifiers": {"cardKingdomId": "32003", "cardsphereId": "46830", "mcmId": "8527", "mcmMetaId": "297", "mtgjsonV4Id": "a7e48b38-8b16-5fab-9310-a2b6bf8dba6c", "mtgoFoilId": "7478", "mtgoId": "7477", "multiverseId": "3733", "scryfallId": "7e129be5-e2c5-4f69-b8e8-539ac2085c7a", "scryfallIllustrationId": "e66e8543-52b2-4bce-a8b2-c53f15f9c5d1", "scryfallOracleId": "c39112ab-ee1f-4f00-b18b-692b5fe32b80", "tcgplayerProductId": "5804"}, "isFoil": false, "language": "English", "layout": "normal", "legalities": {"commander": "Legal", "duel": "Legal", "legacy": "Legal", "paupercommander": "Restricted", "penny": "Legal", "premodern": "Legal", "vintage": "Legal"}, "manaCost": "{1}{B}{R}", "manaValue": 3.0, "name": "Army Ants", "number": "126", "power": "1", "printings": ["PLIST", "VIS"], "purchaseUrls": {"cardKingdom": "https://mtgjson.com/links/c495a1ae1cc3dcf5", "cardmarket": "https://mtgjson.com/links/4bcdc686815fa3ff", "tcgplayer": "https://mtgjson.com/links/72e10fef95c63059"}, "rarity": "uncommon", "rulings": [], "setCode": "VIS", "subtypes": ["Insect"], "supertypes": [], "text": "{T}, Sacrifice a land: Destroy target land.", "toughness": "1", "type": "Creature — Insect", "types": ["Creature"], "uuid": "89ce82ca-9f26-5471-a1a3-555aa12b791b"}, {"artist": "Dan Frazier", "availability": ["mtgo", "paper"], "boosterTypes": ["draft"], "borderColor": "black", "colorIdentity": ["G"], "colors": ["G"], "convertedManaCost": 5.0, "count": 1, "edhrecRank": 13228, "finishes": ["nonfoil"], "flavorText": "Few of Rath's rivers follow a steady course, so many new channels are carved for them.", "foreignData": [{"language": "German", "name": "Schmutzpanzerwurm", "text": "Immer wenn ein Gegner ein Land ausspielt, lege eine +1/+1 Marke auf den Schmutzpanzerwurm.", "type": "Beschwörung eines Wurms"}, {"language": "Spanish", "name": "Sierpe de los cultivos"}, {"language": "French", "name": "Guivre des tourbes"}, {"language": "Italian", "name": "Wurm Manto-di-Fango"}, {"language": "Japanese", "name": "泥衣のワーム"}, {"language": "Portuguese (Brazil)", "name": "Vorme Crista de Pó"}], "frameVersion": "1997", "hasFoil": false, "hasNonFoil": true, "identifiers": {"cardKingdomId": "28069", "cardsphereId": "43138", "mcmId": "8850", "mcmMetaId": "1496", "mtgjsonV4Id": "3154e584-3fd0-5e05-b8b6-7c3cf0d9da04", "mtgoFoilId": "9820", "mtgoId": "9819", "multiverseId": "4755", "scryfallId": "a9e2df7d-5d72-4a32-a453-6d8611f0d63c", "scryfallIllustrationId": "c4cc8456-361f-4009-82d1-c5aaa85ba054", "scryfallOracleId": "608293f1-34aa-4e55-8389-73f975858de6", "tcgplayerProductId": "5520"}, "isFoil": false, "language": "English", "layout": "normal", "legalities": {"commander": "Legal", "duel": "Legal", "legacy": "Legal", "penny": "Legal", "premodern": "Legal", "vintage": "Legal"}, "manaCost": "{4}{G}", "manaValue": 5.0, "name": "Dirtcowl Wurm", "number": "221", "power": "3", "printings": ["BRB", "PRM", "PTMP", "TMP"], "purchaseUrls": {"cardKingdom": "https://mtgjson.com/links/8998ba239d2dacec", "cardmarket": "https://mtgjson.com/links/32563b0b5109f352", "tcgplayer": "https://mtgjson.com/links/2236ca4b48810326"}, "rarity": "rare", "rulings": [{"date": "2004-10-04", "text": "A spell or ability that tells a player to “put a land onto the battlefield” does not count as playing a land."}], "setCode": "TMP", "subtypes": ["Wurm"], "supertypes": [], "text": "Whenever an opponent plays a land, put a +1/+1 counter on Dirtcowl Wurm.", "toughness": "4", "type": "Creature — Wurm", "types": ["Creature"], "uuid": "51cd21e5-3486-5fe4-acd3-0a57d1de4995"}, {"artist": "Dermot Power", "availability": ["mtgo", "paper"], "boosterTypes": ["draft"], "borderColor": "black", "colorIdentity": ["R"], "colors": ["R"], "convertedManaCost": 4.0, "count": 2, "edhrecRank": 22536, "finishes": ["nonfoil"], "flavorText": "\"Stay.\"", "foreignData": [{"language": "German", "name": "Monsterhund", "text": "Der Monsterhund kann nur angreifen, wenn Du mehr Länder als der verteidigende Spieler kontrollierst.\nDer Monsterhund kann nur blocken, wenn Du mehr Länder als der angreifende Spieler kontrollierst.", "type": "Beschwörung eines Hundes"}, {"language": "Spanish", "name": "Sabueso monstruoso"}, {"language": "French", "name": "Chien monstrueux"}, {"language": "Italian", "name": "Segugio Mostruoso"}, {"language": "Japanese", "name": "巨怪なる猟犬"}, {"language": "Portuguese (Brazil)", "name": "Sabujo Monstruoso"}], "frameVersion": "1997", "hasFoil": false, "hasNonFoil": true, "identifiers": {"cardKingdomId": "17065", "cardsphereId": "17234", "mcmId": "9317", "mcmMetaId": "3716", "mtgjsonV4Id": "71aec7b3-e733-59fe-8a9a-a833642470a0", "mtgoFoilId": "10716", "mtgoId": "10715", "multiverseId": "6128", "scryfallId": "d5066b1b-3910-4434-83d6-030851f20bcf", "scryfallIllustrationId": "dc6a0111-aa67-4643-ab21-6b20a0d726d3", "scryfallOracleId": "97589fbb-3bd9-49c9-b8d8-bdc895a7f1e6", "tcgplayerProductId": "4356"}, "isFoil": false, "language": "English", "layout": "normal", "legalities": {"commander": "Legal", "duel": "Legal", "legacy": "Legal", "penny": "Legal", "premodern": "Legal", "vintage": "Legal"}, "manaCost": "{3}{R}", "manaValue": 4.0, "name": "Monstrous Hound", "number": "89", "power": "4", "printings": ["EXO", "PEXO", "PRM"], "purchaseUrls": {"cardKingdom": "https://mtgjson.com/links/6c213e09208f63cb", "cardmarket": "https://mtgjson.com/links/8426c031b5cac9ee", "tcgplayer": "https://mtgjson.com/links/616276c3947d5344"}, "rarity": "rare", "rulings": [], "setCode": "EXO", "subtypes": ["Dog"], "supertypes": [], "text": "Monstrous Hound can't attack unless you control more lands than defending player.\nMonstrous Hound can't block unless you control more lands than attacking player.", "toughness": "4", "type": "Creature — Dog", "types": ["Creature"], "uuid": "c851f73d-d85a-5439-a4ef-bab1cedfcafd"}, {"artist": "Pete Venters", "availability": ["mtgo", "paper"], "boosterTypes": ["draft"], "borderColor": "black", "colorIdentity": ["R"], "colors": ["R"], "convertedManaCost": 2.0, "count": 3, "edhrecRank": 12112, "finishes": ["nonfoil"], "flavorText": "They wouldn't know their house from a charred hole in the ground.", "foreignData": [{"language": "German", "name": "Orksiedler", "text": "{X}{X}{R}, {T}, opfere die Orksiedler: Zerstöre X Länder Deiner Wahl.", "type": "Beschwörung von Orks"}, {"language": "Spanish", "name": "Colonos orcos"}, {"language": "French", "name": "Colons orques"}, {"language": "Italian", "name": "Orchi Coloni"}, {"language": "Japanese", "name": "オークの移住者"}, {"language": "Portuguese (Brazil)", "name": "Colonizadores Orcs"}], "frameVersion": "1997", "hasFoil": false, "hasNonFoil": true, "identifiers": {"cardKingdomId": "33112", "cardsphereId": "47168", "mcmId": "8680", "mcmMetaId": "4015", "mtgjsonV4Id": "691a9524-bd2b-5f13-bb59-b90d134a7f0d", "mtgoFoilId": "9418", "mtgoId": "9417", "multiverseId": "4558", "scryfallId": "d54764f6-6f65-405c-ba30-1e485ce3fe21", "scryfallIllustrationId": "8f9d05e2-b56a-45cb-ace0-f8ae0024b197", "scryfallOracleId": "8b8d4ae0-0d18-4f06-a883-0edff494d06b", "tcgplayerProductId": "6079"}, "isFoil": false, "language": "English", "layout": "normal", "legalities": {"commander": "Legal", "duel": "Legal", "legacy": "Legal", "paupercommander": "Restricted", "premodern": "Legal", "vintage": "Legal"}, "manaCost": "{1}{R}", "manaValue": 2.0, "name": "Orcish Settlers", "number": "112", "power": "1", "printings": ["WC98", "WTH"], "purchaseUrls": {"cardKingdom": "https://mtgjson.com/links/f4a3daf0262089ff", "cardmarket": "https://mtgjson.com/links/04aa3216d587c22c", "tcgplayer": "https://mtgjson.com/links/b3599809329a2ba5"}, "rarity": "uncommon", "rulings": [], "setCode": "WTH", "subtypes": ["Orc"], "supertypes": [], "text": "{X}{X}{R}, {T}, Sacrifice Orcish Settlers: Destroy X target lands.", "toughness": "1", "type": "Creature — Orc", "types": ["Creature"], "uuid": "ec037601-f72d-58df-aa90-0cadf9134a61"}, {"artist": "Daniel Gelon", "availability": ["paper"], "boosterTypes": ["draft"], "borderColor": "white", "colorIdentity": ["R"], "colors": ["R"], "convertedManaCost": 5.0, "count": 1, "edhrecRank": 22686, "finishes": ["nonfoil"], "flavorText": "It's bigger than it thinks.", "foreignData": [{"language": "German", "name": "Orgg", "text": "Verursacht Trampelschaden\nDer Orgg kann nicht angreifen, wenn der verteidigende Spieler eine ungetappte Kreatur mit Stärke 3 oder größer kontrolliert.\nDer Orgg kann nicht deklariert werden, angreifende Kreaturen mit Stärke 3 oder größer zu blocken.", "type": "Beschwörung eines Orggs"}, {"language": "Spanish", "name": "Orgg"}, {"language": "French", "name": "Orgg"}, {"language": "Italian", "name": "Orgg"}, {"language": "Japanese", "name": "オーグ"}, {"language": "Portuguese (Brazil)", "name": "Orgg"}], "frameVersion": "1997", "hasFoil": false, "hasNonFoil": true, "identifiers": {"cardKingdomId": "11287", "cardsphereId": "1443", "mcmId": "9631", "mcmMetaId": "4027", "mtgjsonV4Id": "495f75df-1daf-5600-b606-36f7dd09714f", "multiverseId": "4080", "scryfallId": "c7eef087-8500-4fca-a10a-ff65d348bcb1", "scryfallIllustrationId": "7e1e4e71-0c70-4d87-bb4a-de33bdb183ed", "scryfallOracleId": "f6ea2b1b-1403-4ccd-a23c-48e0e81ceb91", "tcgplayerProductId": "2303"}, "isFoil": false, "isReprint": true, "keywords": ["Trample"], "language": "English", "layout": "normal", "legalities": {"commander": "Legal", "duel": "Legal", "legacy": "Legal", "modern": "Legal", "oldschool": "Legal", "penny": "Legal", "premodern": "Legal", "vintage": "Legal"}, "manaCost": "{3}{R}{R}", "manaValue": 5.0, "name": "Orgg", "number": "259", "power": "6", "printings": ["5ED", "FEM", "PTC", "TSB"], "purchaseUrls": {"cardKingdom": "https://mtgjson.com/links/66158c74a197ea96", "cardmarket": "https://mtgjson.com/links/24a39998c2f7ad80", "tcgplayer": "https://mtgjson.com/links/28d8c501769274df"}, "rarity": "rare", "rulings": [{"date": "2004-10-04", "text": "Whether or not the creatures could attack or block is not important, just whether or not the defending player controls such a creature."}], "setCode": "5ED", "subtypes": ["Orgg"], "supertypes": [], "text": "Trample\nOrgg can't attack if defending player controls an untapped creature with power 3 or greater.\nOrgg can't block creatures with power 3 or greater.", "toughness": "6", "type": "Creature — Orgg", "types": ["Creature"], "uuid": "12dca2b9-a9a2-57b7-97d2-4e1234e1d1c1"}, {"artist": "Ron Spencer", "availability": ["mtgo", "paper"], "boosterTypes": ["draft"], "borderColor": "black", "colorIdentity": ["B"], "colors": ["B"], "convertedManaCost": 2.0, "count": 1, "edhrecRank": 14989, "finishes": ["nonfoil"], "flavorText": "Its respiration is your expiration.", "foreignData": [{"language": "German", "name": "Plagenbringer", "text": "XX{B}: Zerstöre eine nicht-schwarze Kreatur Deiner Wahl mit Gesamtspruchkosten von X.", "type": "Beschwörung eines Zombies"}, {"language": "Spanish", "name": "Portador de la peste"}, {"language": "French", "name": "Porteur de peste"}, {"language": "Italian", "name": "Untore"}, {"language": "Japanese", "name": "疫病媒体"}, {"language": "Portuguese (Brazil)", "name": "Portador da Peste"}], "frameVersion": "1997", "hasFoil": false, "hasNonFoil": true, "identifiers": {"cardKingdomId": "17083", "cardsphereId": "17252", "mcmId": "9299", "mcmMetaId": "4250", "mtgjsonV4Id": "e0b3edab-e4c1-5053-a8cf-d4b844d342cb", "mtgoFoilId": "10474", "mtgoId": "10473", "multiverseId": "5200", "scryfallId": "a8493df6-9954-4e33-867c-ca4bcf3953b2", "scryfallIllustrationId": "69464441-72e6-4937-9060-dabfbe950005", "scryfallOracleId": "f8cc1dc4-740d-4c5b-ac51-7355730a6595", "tcgplayerProductId": "4374"}, "isFoil": false, "language": "English", "layout": "normal", "legalities": {"commander": "Legal", "duel": "Legal", "legacy": "Legal", "premodern": "Legal", "vintage": "Legal"}, "manaCost": "{1}{B}", "manaValue": 2.0, "name": "Plaguebearer", "number": "71", "power": "1", "printings": ["EXO"], "purchaseUrls": {"cardKingdom": "https://mtgjson.com/links/94205d8b8f8dcd0f", "cardmarket": "https://mtgjson.com/links/2505e7a67a2f065c", "tcgplayer": "https://mtgjson.com/links/1c9027c8fdac0a9f"}, "rarity": "rare", "rulings": [], "setCode": "EXO", "subtypes": ["Zombie"], "supertypes": [], "text": "{X}{X}{B}: Destroy target nonblack creature with mana value X.", "toughness": "1", "type": "Creature — Zombie", "types": ["Creature"], "uuid": "5b7fdf35-7a82-5481-a97d-ff2c87e43afd"}, {"artist": "Daren Bader", "availability": ["mtgo", "paper"], "boosterTypes": ["draft"], "borderColor": "black", "colorIdentity": ["R"], "colors": ["R"], "convertedManaCost": 4.0, "count": 1, "edhrecRank": 14991, "finishes": ["nonfoil"], "flavorText": "Build something and the baboons will tear it down. Leave the pieces lying and they will scatter them.", "foreignData": [{"language": "German", "name": "Zerstörerische Paviane", "text": "Wenn die Zerstörerischen Paviane ins Spiel kommen, zerstöre ein Nicht-Standardland Deiner Wahl.", "type": "Beschwörung von Menschenaffen"}, {"language": "Spanish", "name": "Mandriles voraces"}, {"language": "French", "name": "Babouins voraces"}, {"language": "Italian", "name": "Babbuini Famelici"}, {"language": "Japanese", "name": "貪欲なるヒヒ"}, {"language": "Portuguese (Brazil)", "name": "Babuínos Vorazes"}], "frameVersion": "1997", "hasFoil": false, "hasNonFoil": true, "identifiers": {"cardKingdomId": "17090", "cardsphereId": "17259", "mcmId": "9325", "mcmMetaId": "4528", "mtgjsonV4Id": "a74335fa-e06f-53d9-a8da-9fcb6483101e", "mtgoFoilId": "10478", "mtgoId": "10477", "multiverseId": "5207", "scryfallId": "6d00b68b-8b6a-48c9-8911-2a3270897091", "scryfallIllustrationId": "b8ae1883-542f-4544-939b-913eb834aab4", "scryfallOracleId": "1d9bd0a5-3ba0-44e5-9cb3-966f6b9dc14a", "tcgplayerProductId": "4381"}, "isFoil": false, "language": "English", "layout": "normal", "legalities": {"commander": "Legal", "duel": "Legal", "legacy": "Legal", "penny": "Legal", "premodern": "Legal", "vintage": "Legal"}, "manaCost": "{3}{R}", "manaValue": 4.0, "name": "Ravenous Baboons", "number": "97", "power": "2", "printings": ["EXO"], "purchaseUrls": {"cardKingdom": "https://mtgjson.com/links/6b5c226e6c12699b", "cardmarket": "https://mtgjson.com/links/4adb579e1be992e9", "tcgplayer": "https://mtgjson.com/links/a0db28a6022c0c5f"}, "rarity": "rare", "rulings": [{"date": "2004-10-04", "text": "If there is no non-basic land to destroy, the ability does nothing."}, {"date": "2004-10-04", "text": "You have to pick one of your own non-basic lands if the opponent does not have any and you do."}], "setCode": "EXO", "subtypes": ["Monkey"], "supertypes": [], "text": "When Ravenous Baboons enters the battlefield, destroy target nonbasic land.", "toughness": "2", "type": "Creature — Monkey", "types": ["Creature"], "uuid": "5ededc32-1479-50cb-86ef-646eee6802df"}, {"artist": "Una Fricker", "availability": ["mtgo", "paper"], "boosterTypes": ["draft"], "borderColor": "black", "colorIdentity": ["G"], "colors": ["G"], "convertedManaCost": 3.0, "count": 2, "edhrecRank": 12331, "finishes": ["nonfoil"], "flavorText": "\"Is it true that the apes wear furs of gold when they marry?\"\n—Rana, Suq'Ata market fool", "foreignData": [{"language": "German", "name": "Uktabi-Orangutan", "text": "Wenn der Uktabi-Orangutan ins Spiel kommt, zerstöre ein Artefakt Deiner Wahl.", "type": "Beschwörung eines Menschenaffen"}, {"language": "Spanish", "name": "Orangután de Uktabi"}, {"language": "French", "name": "Orang-outang de l'Ouktabi"}, {"language": "Italian", "name": "Orango di Uktabi"}, {"language": "Japanese", "name": "ウークタビー・オランウータン"}, {"language": "Portuguese (Brazil)", "name": "Orangotango de Uktabi"}], "frameVersion": "1997", "hasFoil": false, "hasNonFoil": true, "identifiers": {"cardKingdomId": "32149", "cardsphereId": "46976", "mcmId": "8474", "mcmMetaId": "6202", "mtgjsonV4Id": "cd3cc62b-473d-51d4-9f43-26eff63e02f1", "mtgoFoilId": "7770", "mtgoId": "7769", "multiverseId": "3680", "scryfallId": "101c7d58-43cc-4ebd-87f1-2016fbff56dd", "scryfallIllustrationId": "cb506e13-0599-440a-be3f-6b319c5c6a5e", "scryfallOracleId": "6cc07a7e-e70c-45c5-83c5-a2704e57dbc5", "tcgplayerProductId": "5950"}, "isFoil": false, "language": "English", "layout": "normal", "legalities": {"commander": "Legal", "duel": "Legal", "legacy": "Legal", "paupercommander": "Restricted", "premodern": "Legal", "vintage": "Legal"}, "manaCost": "{2}{G}", "manaValue": 3.0, "name": "Uktabi Orangutan", "number": "123", "power": "2", "printings": ["6ED", "PAL00", "PRM", "VIS", "WC00", "WC97", "WC98", "WC99"], "purchaseUrls": {"cardKingdom": "https://mtgjson.com/links/902608c03e8fab6d", "cardmarket": "https://mtgjson.com/links/2bd93f51f9ba93c4", "tcgplayer": "https://mtgjson.com/links/ee80d76134653631"}, "rarity": "uncommon", "rulings": [], "setCode": "VIS", "subtypes": ["Ape"], "supertypes": [], "text": "When Uktabi Orangutan enters the battlefield, destroy target artifact.", "toughness": "2", "type": "Creature — Ape", "types": ["Creature"], "uuid": "04eec290-7289-563e-a320-a697121e0c3a"}, {"artist": "Ron Spencer", "availability": ["mtgo", "paper"], "boosterTypes": ["draft"], "borderColor": "black", "colorIdentity": ["B"], "colors": ["B"], "convertedManaCost": 2.0, "count": 3, "edhrecRank": 6463, "finishes": ["nonfoil"], "flavorText": "Greven *il*-Vec lifted Vhati off his feet. \"The fall will give you time to think on your failure.\"", "foreignData": [{"language": "German", "name": "Teuflisches Edikt", "text": "Ein Spieler Deiner Wahl opfert Kreatur.", "type": "Spontanzauber"}, {"language": "Spanish", "name": "Ley diabólica"}, {"language": "French", "name": "Edit diabolique"}, {"language": "Italian", "name": "Editto Diabolico"}, {"language": "Japanese", "name": "悪魔の布告"}, {"language": "Portuguese (Brazil)", "name": "Édito Diabólico"}], "frameVersion": "1997", "hasFoil": false, "hasNonFoil": true, "identifiers": {"cardKingdomId": "28068", "cardsphereId": "43137", "mcmId": "8757", "mcmMetaId": "1477", "mtgjsonV4Id": "3909796d-172f-56f8-89fb-645c8c82d4b0", "mtgoFoilId": "9512", "mtgoId": "9511", "multiverseId": "4656", "scryfallId": "a2ecf2ee-1e2d-4ab2-8b2c-717c794b09b2", "scryfallIllustrationId": "080c6f23-5a4d-4a8d-99f3-4ee0ce252f86", "scryfallOracleId": "058917c1-21ab-488a-9f9c-591c55f3c596", "tcgplayerProductId": "5519"}, "isFoil": false, "language": "English", "layout": "normal", "legalities": {"commander": "Legal", "duel": "Legal", "legacy": "Legal", "modern": "Legal", "pauper": "Legal", "paupercommander": "Legal", "penny": "Legal", "premodern": "Legal", "vintage": "Legal"}, "manaCost": "{1}{B}", "manaValue": 2.0, "name": "Diabolic Edict", "number": "128", "printings": ["A25", "BTD", "MB1", "MH1", "MP2", "PAL01", "PMEI", "PRM", "TMP", "TPR", "WC99"], "purchaseUrls": {"cardKingdom": "https://mtgjson.com/links/b28dfc36a17a6526", "cardmarket": "https://mtgjson.com/links/ecda5015388865d3", "tcgplayer": "https://mtgjson.com/links/638004833ea5ec4b"}, "rarity": "common", "rulings": [], "setCode": "TMP", "subtypes": [], "supertypes": [], "text": "Target player sacrifices a creature.", "type": "Instant", "types": ["Instant"], "uuid": "d4c7a523-fa21-58dc-8837-b456d77a73f5"}, {"artist": "Scott M. Fischer", "availability": ["paper"], "boosterTypes": ["draft"], "borderColor": "white", "colorIdentity": ["R"], "colors": ["R"], "convertedManaCost": 2.0, "count": 4, "edhrecRank": 8536, "finishes": ["nonfoil"], "flavorText": "\"Yes, I think 'toast' is an appropriate description.\"\n—Jaya Ballard, task mage", "foreignData": [{"language": "German", "name": "Einäscherung", "text": "Die Einäscherung fügt einem Spieler oder einer Kreatur Deiner Wahl 3 Schadenspunkte zu. Kreaturen, denen die Einäscherung in diesem Zug Schaden zugefügt hat, können nicht regenerieren.", "type": "Spontanzauber"}, {"language": "Spanish", "name": "Incinerar"}, {"language": "French", "name": "Incinération"}, {"language": "Italian", "name": "Incenerire"}, {"language": "Japanese", "name": "火葬"}, {"language": "Portuguese (Brazil)", "name": "Incinerar"}], "frameVersion": "1997", "hasFoil": false, "hasNonFoil": true, "identifiers": {"cardKingdomId": "11201", "cardsphereId": "1351", "mcmId": "9614", "mcmMetaId": "2843", "mtgjsonV4Id": "390729ae-d5c2-59c3-a8f9-685e6a250f4f", "multiverseId": "4063", "scryfallId": "aa0f7e1f-bcb5-414f-a2e9-6a158fec2ff5", "scryfallIllustrationId": "583cf9f8-9906-48c6-85bd-27cdfe43c5ce", "scryfallOracleId": "d8fd7a34-8418-4e98-b79b-119c4348c667", "tcgplayerProductId": "2211"}, "isFoil": false, "isReprint": true, "language": "English", "layout": "normal", "legalities": {"commander": "Legal", "duel": "Legal", "legacy": "Legal", "modern": "Legal", "pauper": "Legal", "paupercommander": "Legal", "penny": "Legal", "premodern": "Legal", "vintage": "Legal"}, "manaCost": "{1}{R}", "manaValue": 2.0, "name": "Incinerate", "number": "242", "printings": ["10E", "5ED", "CST", "DD2", "DKM", "DPA", "ICE", "JVC", "M12", "ME2", "MIR", "P08", "PLGM", "PRM", "PS11", "PTC", "WC97", "WC98"], "purchaseUrls": {"cardKingdom": "https://mtgjson.com/links/6fa5a7ac6fa44ad7", "cardmarket": "https://mtgjson.com/links/a8b4446832f91b67", "tcgplayer": "https://mtgjson.com/links/d263896a91080355"}, "rarity": "common", "rulings": [{"date": "2007-07-15", "text": "Regeneration abilities that would affect that creature can still be activated; they just won’t do anything. The creature can’t be regenerated for any reason, even if an effect other than Incinerate would deal lethal damage to it or otherwise destroy it."}], "setCode": "5ED", "subtypes": [], "supertypes": [], "text": "Incinerate deals 3 damage to any target. A creature dealt damage this way can't be regenerated this turn.", "type": "Instant", "types": ["Instant"], "uuid": "e0df82de-4ada-57c8-af9a-1389f441681e"}, {"artist": "D. Alexander Gregory", "availability": ["mtgo", "paper"], "boosterTypes": ["draft"], "borderColor": "black", "colorIdentity": ["R"], "colors": ["R"], "convertedManaCost": 1.0, "count": 2, "edhrecRank": 11272, "finishes": ["nonfoil"], "foreignData": [{"language": "German", "name": "Brennende Berührung", "text": "Rückkauf 4\nDie Brennende Berührung fügt einer Kreatur oder einem Spieler Deiner Wahl 1 Schadenspunkt zu.", "type": "Spontanzauber"}, {"language": "Spanish", "name": "Toque abrasador"}, {"language": "French", "name": "Effleurement du feu"}, {"language": "Italian", "name": "Tocco Bruciante"}, {"language": "Japanese", "name": "ふにゃふにゃ"}, {"language": "Portuguese (Brazil)", "name": "Toque Cauterizante"}], "frameVersion": "1997", "hasFoil": false, "hasNonFoil": true, "identifiers": {"cardKingdomId": "28257", "cardsphereId": "43334", "mcmId": "8936", "mcmMetaId": "5015", "mtgjsonV4Id": "795f1d85-4f67-5035-8b49-15f958651e3b", "mtgoFoilId": "10076", "mtgoId": "10075", "multiverseId": "4843", "scryfallId": "e9091667-d5a8-4978-9023-032ff65f9642", "scryfallIllustrationId": "8c572ab1-7a90-4c02-8f89-871606c054a4", "scryfallOracleId": "1cd9a3ba-a115-4e59-983d-605e4435f3a8", "tcgplayerProductId": "5716"}, "isFoil": false, "keywords": ["Buyback"], "language": "English", "layout": "normal", "legalities": {"commander": "Legal", "duel": "Legal", "legacy": "Legal", "premodern": "Legal", "vintage": "Legal"}, "manaCost": "{R}", "manaValue": 1.0, "name": "Searing Touch", "number": "201", "printings": ["TMP", "TPR"], "purchaseUrls": {"cardKingdom": "https://mtgjson.com/links/00e48efeb57982af", "cardmarket": "https://mtgjson.com/links/882318e3d4e19533", "tcgplayer": "https://mtgjson.com/links/a3a0f628551ff0f7"}, "rarity": "uncommon", "rulings": [], "setCode": "TMP", "subtypes": [], "supertypes": [], "text": "Buyback {4} (You may pay an additional {4} as you cast this spell. If you do, put this card into your hand as it resolves.)\nSearing Touch deals 1 damage to any target.", "type": "Instant", "types": ["Instant"], "uuid": "ad27bc6c-a59b-5565-8b45-57642eec6de7"}, {"artist": "Richard Kane Ferguson", "availability": ["paper"], "boosterTypes": ["draft"], "borderColor": "white", "colorIdentity": ["R"], "colors": ["R"], "convertedManaCost": 1.0, "count": 2, "edhrecRank": 1430, "finishes": ["nonfoil"], "foreignData": [{"language": "German", "name": "Erdbeben", "text": "Das Erdbeben fügt allen nichtfliegenden Kreaturen und allen Spielern X Schadenspunkte zu.", "type": "Hexerei"}, {"language": "Spanish", "name": "Terremoto"}, {"language": "French", "name": "Tremblement de terre"}, {"language": "Italian", "name": "Terremoto"}, {"language": "Japanese", "name": "地震"}, {"language": "Portuguese (Brazil)", "name": "Terremoto"}], "frameVersion": "1997", "hasFoil": false, "hasNonFoil": true, "identifiers": {"cardKingdomId": "11118", "cardsphereId": "1266", "mcmId": "9595", "mcmMetaId": "1694", "mtgjsonV4Id": "c7b04f94-5c6b-58ce-b641-5c6acba5cdf8", "multiverseId": "4044", "scryfallId": "01bde909-899d-4efc-aac5-57b69fa764db", "scryfallIllustrationId": "f33d1a28-fb86-4731-992e-337ba588c2d1", "scryfallOracleId": "9a40614b-50a3-422c-849e-53c8b7d3d204", "tcgplayerProductId": "2126"}, "isFoil": false, "isReprint": true, "language": "English", "layout": "normal", "legalities": {"commander": "Legal", "duel": "Legal", "legacy": "Legal", "modern": "Legal", "penny": "Legal", "premodern": "Legal", "vintage": "Legal"}, "manaCost": "{X}{R}", "manaValue": 1.0, "name": "Earthquake", "number": "223", "printings": ["2ED", "3ED", "4BB", "4ED", "5ED", "6ED", "7ED", "C15", "C17", "CED", "CEI", "CM2", "CMA", "CMD", "FBB", "LEA", "LEB", "M10", "P02", "POR", "PTC", "SUM", "WC97", "WC99"], "purchaseUrls": {"cardKingdom": "https://mtgjson.com/links/039497c188328321", "cardmarket": "https://mtgjson.com/links/3b5b86bc586bec78", "tcgplayer": "https://mtgjson.com/links/06d6c59277293bb9"}, "rarity": "rare", "rulings": [{"date": "2004-10-04", "text": "Whether or not a creature is without flying is only checked on resolution."}], "setCode": "5ED", "subtypes": [], "supertypes": [], "text": "Earthquake deals X damage to each creature without flying and each player.", "type": "Sorcery", "types": ["Sorcery"], "uuid": "8d9cdc86-3d58-5a9e-af43-9ec05e78cf7e"}, {"artist": "Paolo Parente", "availability": ["mtgo", "paper"], "boosterTypes": ["draft"], "borderColor": "black", "colorIdentity": ["R"], "colors": ["R"], "convertedManaCost": 4.0, "count": 2, "edhrecRank": 20643, "finishes": ["nonfoil"], "foreignData": [{"language": "German", "name": "Schmelzsteinflut", "text": "Rückkauf -Zahle 3 Lebenspunkte, wirf eine zufällig bestimmte Karte aus Deiner Hand ab.\nZerstöre ein Land Deiner Wahl.", "type": "Hexerei"}, {"language": "Spanish", "name": "Inundación de piedra variable"}, {"language": "French", "name": "Flot de fluipierre"}, {"language": "Italian", "name": "Inondazione di Mutaroccia"}, {"language": "Japanese", "name": "流動石の洪水"}, {"language": "Portuguese (Brazil)", "name": "Inundacão de Rochafluente"}], "frameVersion": "1997", "hasFoil": false, "hasNonFoil": true, "identifiers": {"cardKingdomId": "17036", "cardsphereId": "17205", "mcmId": "9311", "mcmMetaId": "2127", "mtgjsonV4Id": "0ceb69bb-860e-5c4e-88b3-a931d9aa9fa1", "mtgoFoilId": "10732", "mtgoId": "10731", "multiverseId": "6120", "scryfallId": "8bcda003-6fac-4879-87e6-ec0c115630ba", "scryfallIllustrationId": "bae93852-097c-41b8-b3e5-b8c4407981c6", "scryfallOracleId": "7f77de5d-1088-42d0-8f68-5633aeab0d74", "tcgplayerProductId": "4327"}, "isFoil": false, "keywords": ["Buyback"], "language": "English", "layout": "normal", "legalities": {"commander": "Legal", "duel": "Legal", "legacy": "Legal", "penny": "Legal", "premodern": "Legal", "vintage": "Legal"}, "manaCost": "{3}{R}", "manaValue": 4.0, "name": "Flowstone Flood", "number": "83", "printings": ["EXO", "WC99"], "purchaseUrls": {"cardKingdom": "https://mtgjson.com/links/a0d399167ae0f258", "cardmarket": "https://mtgjson.com/links/22157876f99ee3b4", "tcgplayer": "https://mtgjson.com/links/06ecda731a7c3dbf"}, "rarity": "uncommon", "rulings": [{"date": "2004-10-04", "text": "You can’t pay the Buyback cost unless you have at least one card in your hand to discard."}], "setCode": "EXO", "subtypes": [], "supertypes": [], "text": "Buyback—Pay 3 life, Discard a card at random. (You may pay 3 life and discard a card at random in addition to any other costs as you cast this spell. If you do, put this card into your hand as it resolves.)\nDestroy target land.", "type": "Sorcery", "types": ["Sorcery"], "uuid": "7cd6dfc0-26da-5719-a25d-8aa8fcbb205f"}, {"artist": "Ron Spencer", "availability": ["mtgo", "paper"], "boosterTypes": ["draft"], "borderColor": "black", "colorIdentity": ["R"], "colors": ["R"], "convertedManaCost": 3.0, "count": 1, "edhrecRank": 16679, "finishes": ["nonfoil"], "foreignData": [{"language": "German", "name": "Hammer aus Bogardan", "text": "Der Hammer aus Bogardan fügt einer Kreatur oder einem Spieler Deiner Wahl 3 Schadenspunkte zu.\n{2}{R}{R}{R}: Bringe den Hammer aus Bogardan zurück auf Deine Hand. Benutze diese Fähigkeit nur während Deiner Versorgungsphase und nur, wenn der Hammer aus Bogardan auf Deinem Friedhof liegt.", "type": "Hexerei"}, {"language": "Spanish", "name": "Martillo de Bogardan"}, {"language": "French", "name": "Marteau du bogardan"}, {"language": "Italian", "name": "Martello di Bogardan"}, {"language": "Japanese", "name": "ボガーダンの鎚"}, {"language": "Portuguese (Brazil)", "name": "Martelo de Bogardan"}], "frameVersion": "1997", "hasFoil": false, "hasNonFoil": true, "identifiers": {"cardKingdomId": "22133", "cardsphereId": "30246", "mcmId": "8232", "mcmMetaId": "2584", "mtgjsonV4Id": "a868e07d-8ad6-5d9f-a3cb-f1b8c54d9271", "mtgoFoilId": "7034", "mtgoId": "7033", "multiverseId": "3452", "scryfallId": "f7285f52-5df0-4f90-9cf7-a57295d90fd4", "scryfallIllustrationId": "588f58c1-8e7c-4d4e-be2a-eec1ec7512f5", "scryfallOracleId": "3089bdd7-87e6-4d0e-ad98-c32e6f861c30", "tcgplayerProductId": "5094"}, "isFoil": false, "language": "English", "layout": "normal", "legalities": {"commander": "Legal", "duel": "Legal", "legacy": "Legal", "modern": "Legal", "penny": "Legal", "premodern": "Legal", "vintage": "Legal"}, "manaCost": "{1}{R}{R}", "manaValue": 3.0, "name": "Hammer of Bogardan", "number": "181", "printings": ["6ED", "8ED", "G02", "MIR", "PD2", "PRM", "WC97", "WC98", "WC99"], "purchaseUrls": {"cardKingdom": "https://mtgjson.com/links/9894804ad3b43bc1", "cardmarket": "https://mtgjson.com/links/ad8064047b562a0e", "tcgplayer": "https://mtgjson.com/links/1817fdc89e776260"}, "rarity": "rare", "rulings": [], "setCode": "MIR", "subtypes": [], "supertypes": [], "text": "Hammer of Bogardan deals 3 damage to any target.\n{2}{R}{R}{R}: Return Hammer of Bogardan from your graveyard to your hand. Activate only during your upkeep.", "type": "Sorcery", "types": ["Sorcery"], "uuid": "cd91a286-01b6-5945-b61b-24829496ee58"}, {"artist": "Charles Gillespie", "availability": ["mtgo", "paper"], "boosterTypes": ["draft"], "borderColor": "black", "colorIdentity": ["B"], "colors": ["B"], "convertedManaCost": 3.0, "count": 4, "edhrecRank": 16061, "finishes": ["nonfoil"], "flavorText": "\"These rains cannot quench; they carve the land's face like a scalpel on flesh.\"\n—Crovax", "foreignData": [{"language": "German", "name": "Tränenschauer", "text": "Zerstöre ein Land Deiner Wahl.", "type": "Hexerei"}, {"language": "Spanish", "name": "Lluvia de lágrimas"}, {"language": "French", "name": "Pluie de larmes"}, {"language": "Italian", "name": "Pioggia di Lacrime"}, {"language": "Japanese", "name": "涙の雨"}, {"language": "Portuguese (Brazil)", "name": "Chuva de Lágrimas"}], "frameVersion": "1997", "hasFoil": false, "hasNonFoil": true, "identifiers": {"cardKingdomId": "28219", "cardsphereId": "43296", "mcmId": "8778", "mcmMetaId": "4480", "mtgjsonV4Id": "d88079f9-7379-530e-b6f1-3f3fb7690dee", "mtgoFoilId": "9994", "mtgoId": "9993", "multiverseId": "4678", "scryfallId": "cad93919-273f-4a26-8ebd-13503dd6b220", "scryfallIllustrationId": "14be1dc2-b2ad-4650-8e9c-14575564a725", "scryfallOracleId": "72cecab3-519e-4a23-9623-b423a5c5a251", "tcgplayerProductId": "5678"}, "isFoil": false, "isReprint": true, "language": "English", "layout": "normal", "legalities": {"commander": "Legal", "duel": "Legal", "legacy": "Legal", "modern": "Legal", "premodern": "Legal", "vintage": "Legal"}, "manaCost": "{1}{B}{B}", "manaValue": 3.0, "name": "Rain of Tears", "number": "149", "printings": ["10E", "MMQ", "POR", "TMP"], "purchaseUrls": {"cardKingdom": "https://mtgjson.com/links/1fe22e02a287a38c", "cardmarket": "https://mtgjson.com/links/a28c91953269eb33", "tcgplayer": "https://mtgjson.com/links/86c7ab1af10ffb1b"}, "rarity": "uncommon", "rulings": [], "setCode": "TMP", "subtypes": [], "supertypes": [], "text": "Destroy target land.", "type": "Sorcery", "types": ["Sorcery"], "uuid": "d6d167eb-eef8-5e90-9300-2a1820520f80"}, {"artist": "Christopher Rush", "availability": ["mtgo", "paper"], "boosterTypes": ["draft"], "borderColor": "black", "colorIdentity": ["R"], "colors": ["R"], "convertedManaCost": 3.0, "count": 4, "edhrecRank": 9093, "finishes": ["nonfoil"], "flavorText": "\"The land shall beg for drink and curse the rain that follows.\"\n—Oracle *en*-Vec", "foreignData": [{"language": "German", "name": "Steinhagel", "text": "Zerstöre ein Land Deiner Wahl.", "type": "Hexerei"}, {"language": "Spanish", "name": "Lluvia de piedras"}, {"language": "French", "name": "Pluie de pierres"}, {"language": "Italian", "name": "Pioggia di Pietre"}, {"language": "Japanese", "name": "石の雨"}, {"language": "Portuguese (Brazil)", "name": "Chuva de Pedras"}], "frameVersion": "1997", "hasFoil": false, "hasNonFoil": true, "identifiers": {"cardKingdomId": "28296", "cardsphereId": "43373", "mcmId": "8941", "mcmMetaId": "5627", "mtgjsonV4Id": "a77fb695-ef6a-554e-b69d-981b337224ad", "mtgoFoilId": "9584", "mtgoId": "9583", "multiverseId": "4850", "scryfallId": "f92548d9-cba6-495f-bef1-73e4519fe336", "scryfallIllustrationId": "4ac9b285-6668-4e76-98d6-dfe03001fad0", "scryfallOracleId": "6e880df6-fc00-43d2-a9c8-f575f40b78c6", "tcgplayerProductId": "5755"}, "isFoil": false, "isReprint": true, "language": "English", "layout": "normal", "legalities": {"commander": "Legal", "duel": "Legal", "gladiator": "Legal", "historic": "Legal", "historicbrawl": "Legal", "legacy": "Legal", "modern": "Legal", "pauper": "Legal", "paupercommander": "Legal", "penny": "Legal", "premodern": "Legal", "vintage": "Legal"}, "manaCost": "{2}{R}", "manaValue": 3.0, "name": "Stone Rain", "number": "206", "printings": ["2ED", "3ED", "4BB", "4ED", "5ED", "6ED", "7ED", "8ED", "9ED", "CED", "CEI", "CHK", "FBB", "FNM", "ICE", "LEA", "LEB", "MIR", "MMQ", "P02", "PLIST", "POR", "PRM", "PTK", "S99", "STA", "SUM", "TMP", "WC00", "WC99"], "purchaseUrls": {"cardKingdom": "https://mtgjson.com/links/b7919f88845b78ec", "cardmarket": "https://mtgjson.com/links/33f465b546360aea", "tcgplayer": "https://mtgjson.com/links/4d9280161b26c008"}, "rarity": "common", "rulings": [], "setCode": "TMP", "subtypes": [], "supertypes": [], "text": "Destroy target land.", "type": "Sorcery", "types": ["Sorcery"], "uuid": "b3befb02-6b2c-5b30-abe7-4faef0181702"}], "name": "Groundbreaker - Advanced Deck", "releaseDate": "1998-06-15", "sideBoard": [{"artist": "Rebecca Guay", "availability": ["mtgo", "paper"], "boosterTypes": ["draft"], "borderColor": "black", "colorIdentity": ["B"], "colors": ["B"], "convertedManaCost": 3.0, "count": 2, "edhrecRank": 14980, "finishes": ["nonfoil"], "flavorText": "\"There will come a time when the voices of soil and seedling will sing only laments.\"\n—Oracle *en*-Vec", "foreignData": [{"language": "German", "name": "Untergang", "text": "Zerstöre alle grünen Kreaturen. Diese Kreaturen können in diesem Zug nicht regenerieren.", "type": "Hexerei"}, {"language": "Spanish", "name": "Perecer"}, {"language": "French", "name": "Trépas"}, {"language": "Italian", "name": "Perire"}, {"language": "Japanese", "name": "非業の死"}, {"language": "Portuguese (Brazil)", "name": "Perecer"}], "frameVersion": "1997", "hasFoil": false, "hasNonFoil": true, "identifiers": {"cardKingdomId": "28205", "cardsphereId": "43280", "mcmId": "8776", "mcmMetaId": "4144", "mtgjsonV4Id": "396eefb0-f9df-5f81-bc5c-ed22524fa21b", "mtgoFoilId": "10000", "mtgoId": "9999", "multiverseId": "4676", "scryfallId": "e47ace1d-73de-44aa-a3fe-2e2a21ebec79", "scryfallIllustrationId": "aefbf475-f60a-434f-9f78-bd0873970172", "scryfallOracleId": "dd84d291-cb7a-4f44-81cd-9f1181bb5ae5", "tcgplayerProductId": "5662"}, "isFoil": false, "language": "English", "layout": "normal", "legalities": {"commander": "Legal", "duel": "Legal", "legacy": "Legal", "premodern": "Legal", "vintage": "Legal"}, "manaCost": "{2}{B}", "manaValue": 3.0, "name": "Perish", "number": "147", "printings": ["6ED", "MB1", "TMP", "WC99"], "purchaseUrls": {"cardKingdom": "https://mtgjson.com/links/d14baf5fe4c8ce8b", "cardmarket": "https://mtgjson.com/links/5bd92aaf1c33c450", "tcgplayer": "https://mtgjson.com/links/31ec55df47e41f5f"}, "rarity": "uncommon", "rulings": [], "setCode": "TMP", "subtypes": [], "supertypes": [], "text": "Destroy all green creatures. They can't be regenerated.", "type": "Sorcery", "types": ["Sorcery"], "uuid": "8c50b2ef-0ebd-52dd-bea1-6363e4b3287b"}, {"artist": "Richard Kane Ferguson", "availability": ["paper"], "boosterTypes": ["draft"], "borderColor": "white", "colorIdentity": ["R"], "colors": ["R"], "convertedManaCost": 1.0, "count": 1, "edhrecRank": 1430, "finishes": ["nonfoil"], "foreignData": [{"language": "German", "name": "Erdbeben", "text": "Das Erdbeben fügt allen nichtfliegenden Kreaturen und allen Spielern X Schadenspunkte zu.", "type": "Hexerei"}, {"language": "Spanish", "name": "Terremoto"}, {"language": "French", "name": "Tremblement de terre"}, {"language": "Italian", "name": "Terremoto"}, {"language": "Japanese", "name": "地震"}, {"language": "Portuguese (Brazil)", "name": "Terremoto"}], "frameVersion": "1997", "hasFoil": false, "hasNonFoil": true, "identifiers": {"cardKingdomId": "11118", "cardsphereId": "1266", "mcmId": "9595", "mcmMetaId": "1694", "mtgjsonV4Id": "c7b04f94-5c6b-58ce-b641-5c6acba5cdf8", "multiverseId": "4044", "scryfallId": "01bde909-899d-4efc-aac5-57b69fa764db", "scryfallIllustrationId": "f33d1a28-fb86-4731-992e-337ba588c2d1", "scryfallOracleId": "9a40614b-50a3-422c-849e-53c8b7d3d204", "tcgplayerProductId": "2126"}, "isFoil": false, "isReprint": true, "language": "English", "layout": "normal", "legalities": {"commander": "Legal", "duel": "Legal", "legacy": "Legal", "modern": "Legal", "penny": "Legal", "premodern": "Legal", "vintage": "Legal"}, "manaCost": "{X}{R}", "manaValue": 1.0, "name": "Earthquake", "number": "223", "printings": ["2ED", "3ED", "4BB", "4ED", "5ED", "6ED", "7ED", "C15", "C17", "CED", "CEI", "CM2", "CMA", "CMD", "FBB", "LEA", "LEB", "M10", "P02", "POR", "PTC", "SUM", "WC97", "WC99"], "purchaseUrls": {"cardKingdom": "https://mtgjson.com/links/039497c188328321", "cardmarket": "https://mtgjson.com/links/3b5b86bc586bec78", "tcgplayer": "https://mtgjson.com/links/06d6c59277293bb9"}, "rarity": "rare", "rulings": [{"date": "2004-10-04", "text": "Whether or not a creature is without flying is only checked on resolution."}], "setCode": "5ED", "subtypes": [], "supertypes": [], "text": "Earthquake deals X damage to each creature without flying and each player.", "type": "Sorcery", "types": ["Sorcery"], "uuid": "8d9cdc86-3d58-5a9e-af43-9ec05e78cf7e"}, {"artist": "Jason Alexander Behnke", "availability": ["mtgo", "paper"], "boosterTypes": ["draft"], "borderColor": "black", "colorIdentity": ["R"], "colors": ["R"], "convertedManaCost": 4.0, "count": 2, "edhrecRank": 9893, "finishes": ["nonfoil"], "flavorText": "\"The fishers will throw out their nets and draw them back filled with dust.\"\n—Oracle *en*-Vec", "foreignData": [{"language": "German", "name": "Kochende See", "text": "Zerstöre alle Inseln.", "type": "Spontanzauber"}, {"language": "Spanish", "name": "Ebullición"}, {"language": "French", "name": "Bouillonnement"}, {"language": "Italian", "name": "Ribollire"}, {"language": "Japanese", "name": "沸騰"}, {"language": "Portuguese (Brazil)", "name": "Ferver"}], "frameVersion": "1997", "hasFoil": false, "hasNonFoil": true, "identifiers": {"cardKingdomId": "28021", "cardsphereId": "43090", "mcmId": "8900", "mcmMetaId": "639", "mtgjsonV4Id": "904e2735-9836-5687-a942-cf6f912ff7bf", "mtgoFoilId": "10084", "mtgoId": "10083", "multiverseId": "4805", "scryfallId": "2fa1c529-44e5-41b6-9704-ae2319f31f13", "scryfallIllustrationId": "a52a19c8-a936-4b8c-8b63-250616ec01ef", "scryfallOracleId": "3a51485b-31b2-4fa5-824a-a919f9d28ca8", "tcgplayerProductId": "5472"}, "isFoil": false, "language": "English", "layout": "normal", "legalities": {"commander": "Legal", "duel": "Legal", "legacy": "Legal", "modern": "Legal", "premodern": "Legal", "vintage": "Legal"}, "manaCost": "{3}{R}", "manaValue": 4.0, "name": "Boil", "number": "165", "printings": ["6ED", "7ED", "8ED", "MP2", "TMP", "WC00", "WC01", "WC98", "WC99"], "purchaseUrls": {"cardKingdom": "https://mtgjson.com/links/61c99221bd7c3eec", "cardmarket": "https://mtgjson.com/links/f351d2770e3f684d", "tcgplayer": "https://mtgjson.com/links/8cdb4910f0c9f106"}, "rarity": "uncommon", "rulings": [], "setCode": "TMP", "subtypes": [], "supertypes": [], "text": "Destroy all Islands.", "type": "Instant", "types": ["Instant"], "uuid": "8fc1cd83-a76a-54b9-85c6-eb60d30c5ffa"}, {"artist": "Daren Bader", "availability": ["mtgo", "paper"], "boosterTypes": ["draft"], "borderColor": "black", "colorIdentity": ["R"], "colors": ["R"], "convertedManaCost": 4.0, "count": 1, "edhrecRank": 14991, "finishes": ["nonfoil"], "flavorText": "Build something and the baboons will tear it down. Leave the pieces lying and they will scatter them.", "foreignData": [{"language": "German", "name": "Zerstörerische Paviane", "text": "Wenn die Zerstörerischen Paviane ins Spiel kommen, zerstöre ein Nicht-Standardland Deiner Wahl.", "type": "Beschwörung von Menschenaffen"}, {"language": "Spanish", "name": "Mandriles voraces"}, {"language": "French", "name": "Babouins voraces"}, {"language": "Italian", "name": "Babbuini Famelici"}, {"language": "Japanese", "name": "貪欲なるヒヒ"}, {"language": "Portuguese (Brazil)", "name": "Babuínos Vorazes"}], "frameVersion": "1997", "hasFoil": false, "hasNonFoil": true, "identifiers": {"cardKingdomId": "17090", "cardsphereId": "17259", "mcmId": "9325", "mcmMetaId": "4528", "mtgjsonV4Id": "a74335fa-e06f-53d9-a8da-9fcb6483101e", "mtgoFoilId": "10478", "mtgoId": "10477", "multiverseId": "5207", "scryfallId": "6d00b68b-8b6a-48c9-8911-2a3270897091", "scryfallIllustrationId": "b8ae1883-542f-4544-939b-913eb834aab4", "scryfallOracleId": "1d9bd0a5-3ba0-44e5-9cb3-966f6b9dc14a", "tcgplayerProductId": "4381"}, "isFoil": false, "language": "English", "layout": "normal", "legalities": {"commander": "Legal", "duel": "Legal", "legacy": "Legal", "penny": "Legal", "premodern": "Legal", "vintage": "Legal"}, "manaCost": "{3}{R}", "manaValue": 4.0, "name": "Ravenous Baboons", "number": "97", "power": "2", "printings": ["EXO"], "purchaseUrls": {"cardKingdom": "https://mtgjson.com/links/6b5c226e6c12699b", "cardmarket": "https://mtgjson.com/links/4adb579e1be992e9", "tcgplayer": "https://mtgjson.com/links/a0db28a6022c0c5f"}, "rarity": "rare", "rulings": [{"date": "2004-10-04", "text": "If there is no non-basic land to destroy, the ability does nothing."}, {"date": "2004-10-04", "text": "You have to pick one of your own non-basic lands if the opponent does not have any and you do."}], "setCode": "EXO", "subtypes": ["Monkey"], "supertypes": [], "text": "When Ravenous Baboons enters the battlefield, destroy target nonbasic land.", "toughness": "2", "type": "Creature — Monkey", "types": ["Creature"], "uuid": "5ededc32-1479-50cb-86ef-646eee6802df"}, {"artist": "Romas Kukalis", "availability": ["mtgo", "paper"], "boosterTypes": ["draft"], "borderColor": "black", "colorIdentity": ["G"], "colors": ["G"], "convertedManaCost": 3.0, "count": 2, "edhrecRank": 6936, "finishes": ["nonfoil"], "flavorText": "\"My horizon was the arcing petals, my new home resplendent with spires of weeds and pillows of fragrant pollen.\"\n—Naimah, Femeref philosopher", "foreignData": [{"language": "German", "name": "Stadt der Einsamkeit", "text": "Jeder Spieler kann Zaubersprüche und Fähigkeiten nur während seines Zuges sprechen bzw. benutzen.", "type": "Verzauberung"}, {"language": "Spanish", "name": "Ciudad de la Soledad"}, {"language": "French", "name": "Cité de solitude"}, {"language": "Italian", "name": "Città della Solitudine"}, {"language": "Japanese", "name": "孤独の都"}, {"language": "Portuguese (Brazil)", "name": "Cidade do Isolamento"}], "frameVersion": "1997", "hasFoil": false, "hasNonFoil": true, "identifiers": {"cardKingdomId": "32013", "cardsphereId": "46840", "mcmId": "8453", "mcmMetaId": "1011", "mtgjsonV4Id": "d7eb7f99-0aed-5d23-8160-99b9a4775224", "mtgoFoilId": "7498", "mtgoId": "7497", "multiverseId": "3659", "scryfallId": "be499b81-bb2d-4f1d-9deb-c8bfcdca8e13", "scryfallIllustrationId": "87d881c4-bda0-46e2-b0c3-5f747a0ab454", "scryfallOracleId": "671458ac-7441-4332-9e59-a42ec8b62f31", "tcgplayerProductId": "5814"}, "isFoil": false, "isReserved": true, "language": "English", "layout": "normal", "legalities": {"commander": "Legal", "duel": "Legal", "legacy": "Legal", "premodern": "Legal", "vintage": "Legal"}, "manaCost": "{2}{G}", "manaValue": 3.0, "name": "City of Solitude", "number": "102", "printings": ["VIS", "WC97"], "purchaseUrls": {"cardKingdom": "https://mtgjson.com/links/14edf178cd87e02e", "cardmarket": "https://mtgjson.com/links/208246eb9a3653d7", "tcgplayer": "https://mtgjson.com/links/d799f921a7e6f88e"}, "rarity": "rare", "rulings": [{"date": "2004-10-04", "text": "City of Solitude can affect abilities of cards that are not on the battlefield because it prevents players from activating those abilities."}, {"date": "2004-10-04", "text": "City of Solitude does not stop triggered abilities from being put on the stack. They are never “activated”."}, {"date": "2009-10-01", "text": "This stops players from activating mana abilities."}], "setCode": "VIS", "subtypes": [], "supertypes": [], "text": "Players can cast spells and activate abilities only during their own turns.", "type": "Enchantment", "types": ["Enchantment"], "uuid": "7cf19545-be13-5449-ae80-f2265fd5c80f"}, {"artist": "Margaret Organ-Kean", "availability": ["mtgo", "paper"], "boosterTypes": ["draft"], "borderColor": "black", "colorIdentity": ["G"], "colors": ["G"], "convertedManaCost": 3.0, "count": 2, "edhrecRank": 11761, "finishes": ["nonfoil"], "flavorText": "\"Peace will come, but whether born of harmony or entropy I cannot say.\"\n—Oracle *en*-Vec", "foreignData": [{"language": "German", "name": "Seelenruhe", "text": "Zerstöre alle Verzauberungen.", "type": "Hexerei"}, {"language": "Spanish", "name": "Tranquillità"}, {"language": "French", "name": "Tranquilité"}, {"language": "Italian", "name": "Tranquillità"}, {"language": "Japanese", "name": "平穏"}, {"language": "Portuguese (Brazil)", "name": "Tranqüilidade"}], "frameVersion": "1997", "hasFoil": false, "hasNonFoil": true, "identifiers": {"cardKingdomId": "28317", "cardsphereId": "43396", "mcmId": "8890", "mcmMetaId": "6113", "mtgjsonV4Id": "7b2b5d2f-27f7-53ed-b82a-c7a52a74a89e", "mtgoFoilId": "9550", "mtgoId": "9549", "multiverseId": "4795", "scryfallId": "160b8060-e755-4a96-9193-b76550d4a6ba", "scryfallIllustrationId": "e6dda5c8-95d2-4d94-8883-f71384d67ceb", "scryfallOracleId": "f671e3c3-cd59-4d06-a1af-5d04892cf74d", "tcgplayerProductId": "5778"}, "isFoil": false, "isReprint": true, "language": "English", "layout": "normal", "legalities": {"commander": "Legal", "duel": "Legal", "legacy": "Legal", "pauper": "Legal", "paupercommander": "Legal", "premodern": "Legal", "vintage": "Legal"}, "manaCost": "{2}{G}", "manaValue": 3.0, "name": "Tranquility", "number": "261", "printings": ["2ED", "3ED", "4BB", "4ED", "5ED", "6ED", "7ED", "BRB", "CED", "CEI", "FBB", "INV", "LEA", "LEB", "MMQ", "PTC", "SUM", "TMP", "TPR"], "purchaseUrls": {"cardKingdom": "https://mtgjson.com/links/5c521aaac70ebb7a", "cardmarket": "https://mtgjson.com/links/c9326fa79cacb98d", "tcgplayer": "https://mtgjson.com/links/feb3f4f1dbf2281a"}, "rarity": "common", "rulings": [], "setCode": "TMP", "subtypes": [], "supertypes": [], "text": "Destroy all enchantments.", "type": "Sorcery", "types": ["Sorcery"], "uuid": "3e0bdc2a-f694-5bd6-9946-6422b35556ce"}, {"artist": "Una Fricker", "availability": ["mtgo", "paper"], "boosterTypes": ["draft"], "borderColor": "black", "colorIdentity": ["G"], "colors": ["G"], "convertedManaCost": 3.0, "count": 2, "edhrecRank": 12331, "finishes": ["nonfoil"], "flavorText": "\"Is it true that the apes wear furs of gold when they marry?\"\n—Rana, Suq'Ata market fool", "foreignData": [{"language": "German", "name": "Uktabi-Orangutan", "text": "Wenn der Uktabi-Orangutan ins Spiel kommt, zerstöre ein Artefakt Deiner Wahl.", "type": "Beschwörung eines Menschenaffen"}, {"language": "Spanish", "name": "Orangután de Uktabi"}, {"language": "French", "name": "Orang-outang de l'Ouktabi"}, {"language": "Italian", "name": "Orango di Uktabi"}, {"language": "Japanese", "name": "ウークタビー・オランウータン"}, {"language": "Portuguese (Brazil)", "name": "Orangotango de Uktabi"}], "frameVersion": "1997", "hasFoil": false, "hasNonFoil": true, "identifiers": {"cardKingdomId": "32149", "cardsphereId": "46976", "mcmId": "8474", "mcmMetaId": "6202", "mtgjsonV4Id": "cd3cc62b-473d-51d4-9f43-26eff63e02f1", "mtgoFoilId": "7770", "mtgoId": "7769", "multiverseId": "3680", "scryfallId": "101c7d58-43cc-4ebd-87f1-2016fbff56dd", "scryfallIllustrationId": "cb506e13-0599-440a-be3f-6b319c5c6a5e", "scryfallOracleId": "6cc07a7e-e70c-45c5-83c5-a2704e57dbc5", "tcgplayerProductId": "5950"}, "isFoil": false, "language": "English", "layout": "normal", "legalities": {"commander": "Legal", "duel": "Legal", "legacy": "Legal", "paupercommander": "Restricted", "premodern": "Legal", "vintage": "Legal"}, "manaCost": "{2}{G}", "manaValue": 3.0, "name": "Uktabi Orangutan", "number": "123", "power": "2", "printings": ["6ED", "PAL00", "PRM", "VIS", "WC00", "WC97", "WC98", "WC99"], "purchaseUrls": {"cardKingdom": "https://mtgjson.com/links/902608c03e8fab6d", "cardmarket": "https://mtgjson.com/links/2bd93f51f9ba93c4", "tcgplayer": "https://mtgjson.com/links/ee80d76134653631"}, "rarity": "uncommon", "rulings": [], "setCode": "VIS", "subtypes": ["Ape"], "supertypes": [], "text": "When Uktabi Orangutan enters the battlefield, destroy target artifact.", "toughness": "2", "type": "Creature — Ape", "types": ["Creature"], "uuid": "04eec290-7289-563e-a320-a697121e0c3a"}, {"artist": "Mark Tedin", "availability": ["paper"], "boosterTypes": ["draft"], "borderColor": "white", "colorIdentity": [], "colors": [], "convertedManaCost": 4.0, "count": 3, "edhrecRank": 588, "finishes": ["nonfoil"], "foreignData": [{"language": "German", "name": "Nevinyrrals Wunderscheibe", "text": "Nevinyrrals Wunderscheibe kommt getappt ins Spiel.\n1, {T}: Zerstöre alle Artefakte, Kreaturen und Verzauberungen.", "type": "Artefakt"}, {"language": "Spanish", "name": "Disco de Nevinyrral"}, {"language": "French", "name": "Disque de Nevinyrral"}, {"language": "Italian", "name": "Disco di Nevinyrral"}, {"language": "Japanese", "name": "ネビニラルの円盤"}, {"language": "Portuguese (Brazil)", "name": "Disco de Nevinyrral"}], "frameVersion": "1997", "hasFoil": false, "hasNonFoil": true, "identifiers": {"cardKingdomId": "11276", "cardsphereId": "1432", "mcmId": "9763", "mcmMetaId": "3884", "mtgjsonV4Id": "6e5b6f69-e43d-56a7-a937-571d343a53f6", "multiverseId": "3803", "scryfallId": "9652c405-17fb-4505-8470-8a2969c73b6b", "scryfallIllustrationId": "c895f461-6194-45b4-b820-6577ed426a3c", "scryfallOracleId": "96230edf-568a-47dd-b877-9d92aa58fac8", "tcgplayerProductId": "2292"}, "isFoil": false, "isReprint": true, "language": "English", "layout": "normal", "legalities": {"commander": "Legal", "duel": "Legal", "legacy": "Legal", "modern": "Legal", "oldschool": "Legal", "penny": "Legal", "premodern": "Legal", "vintage": "Legal"}, "manaCost": "{4}", "manaValue": 4.0, "name": "Nevinyrral's Disk", "number": "391", "printings": ["2ED", "3ED", "4BB", "4ED", "5ED", "ATH", "C13", "C14", "C16", "C17", "CED", "CEI", "CMR", "EMA", "FBB", "LEA", "LEB", "ME1", "MH2", "PRM", "PTC", "SUM", "V10", "VMA", "WC97", "WC98"], "purchaseUrls": {"cardKingdom": "https://mtgjson.com/links/c832d43a470ec81e", "cardmarket": "https://mtgjson.com/links/7e9a6965182cf4c4", "tcgplayer": "https://mtgjson.com/links/923535abbf33a14a"}, "rarity": "rare", "rulings": [{"date": "2020-11-10", "text": "You don't sacrifice Nevinyrral's Disk to activate its ability. It's destroyed as part of the ability's resolution if it's still on the battlefield. If an effect gives Nevinyrral's Disk indestructible or regenerates it, it stays on the battlefield."}], "setCode": "5ED", "subtypes": [], "supertypes": [], "text": "Nevinyrral's Disk enters the battlefield tapped.\n{1}, {T}: Destroy all artifacts, creatures, and enchantments.", "type": "Artifact", "types": ["Artifact"], "uuid": "adc19b3c-24c3-5606-9203-07ab8c2bf513"}], "type": "Advanced Deck"}}